{"data":{"requestedId":1202967480,"inventoryItem":{"itemHash":1202967480,"itemName":"XV0\u300c\u30bf\u30a4\u30e0\u30d6\u30ec\u30fc\u30ab\u30fc\u300d","itemDescription":"\u52c7\u6562\u306a\u4eba\u9593\u306f\u305f\u304f\u3055\u3093\u3044\u308b\u304c\u3001\u3053\u306e\u30b9\u30d1\u30ed\u30fc\u306b\u4e57\u308c\u308b\u306e\u306f\u5f37\u304f\u3066\u751f\u304d\u3066\u3044\u308b\u5974\u3060\u3051\u3060\u3002","icon":"\/common\/destiny_content\/icons\/562bc1ed01580f801e0876392ddf4fec.jpg","secondaryIcon":"\/img\/misc\/missing_icon.png","actionName":"\u6368\u3066\u308b","tierTypeName":"\u30ec\u30b8\u30a7\u30f3\u30c0\u30ea\u30fc","tierType":5,"itemTypeName":"\u30d3\u30fc\u30af\u30eb","bucketTypeHash":2025709351,"primaryBaseStatHash":360359141,"stats":{"360359141":{"statHash":360359141,"value":120,"minimum":120,"maximum":120},"1501155019":{"statHash":1501155019,"value":6,"minimum":6,"maximum":6}},"perkHashes":[],"specialItemType":0,"talentGridHash":2064730451,"equippingBlock":{"weaponSandboxPatternIndex":56,"gearArtArrangementIndex":-1,"defaultDyes":[],"lockedDyes":[{"channelHash":2025709351,"dyeHash":1964776802}],"customDyes":[],"customDyeExpression":{"steps":[]},"weaponPatternHash":2027733067},"hasGeometry":false,"statGroupHash":2025709351,"itemLevels":[],"qualityLevel":0,"rewardItemHash":0,"values":{},"itemType":0,"itemSubType":0,"classType":3,"nonTransferrable":false,"exclusive":0,"maxStackSize":1},"talentGrid":{"gridHash":2064730451,"maxGridLevel":0,"gridLevelPerColumn":0,"progressionHash":0,"nodes":[{"nodeIndex":0,"nodeHash":402935547,"row":2,"column":0,"prerequisiteNodeIndexes":[],"binaryPairNodeIndex":-1,"autoUnlocks":true,"lastStepRepeats":false,"isRandom":false,"isRandomRepurchasable":false,"steps":[{"stepIndex":0,"nodeStepHash":1458802667,"nodeStepName":"\u30aa\u30fc\u30d0\u30fc\u30c9\u30e9\u30a4\u30d6","nodeStepDescription":"\u9577\u62bc\u3057\u3067\u3001\u81ea\u5206\u306e\u8eab\u4f53\u3092\u591a\u5c11\u5371\u967a\u306b\u3055\u3089\u3059\u4ee3\u308f\u308a\u306b\u52a0\u901f\u3067\u304d\u308b\u3002","icon":"\/common\/destiny_content\/icons\/12028ee57e77dc48dd23821a3a9d8825.png","damageType":0,"activationRequirement":{"gridLevel":0,"materialRequirementHashes":[]},"canActivateNextStep":false,"nextStepIndex":-1,"isNextStepRandom":false,"perkHashes":[3104860955],"startProgressionBarAtProgress":0,"statHashes":[],"affectsQuality":false,"trueStepIndex":0,"truePropertyIndex":0,"affectsLevel":false}],"exlusiveWithNodes":[402494132,402641165],"randomStartProgressionBarAtProgression":0},{"nodeIndex":1,"nodeHash":402494132,"row":1,"column":0,"prerequisiteNodeIndexes":[],"binaryPairNodeIndex":-1,"autoUnlocks":true,"lastStepRepeats":false,"isRandom":false,"isRandomRepurchasable":false,"steps":[{"stepIndex":0,"nodeStepHash":1896096036,"nodeStepName":"\u30b9\u30c8\u30e9\u30d5\u30b9\u30e9\u30b9\u30bf","nodeStepDescription":"\u3068\u3067\u7d20\u65e9\u304f\u6a2a\u306b\u52d5\u304f\u3002","icon":"\/common\/destiny_content\/icons\/1ea15f44a8a5f90c111ebbe7dd43ab85.png","damageType":0,"activationRequirement":{"gridLevel":0,"materialRequirementHashes":[]},"canActivateNextStep":false,"nextStepIndex":-1,"isNextStepRandom":false,"perkHashes":[4091143788],"startProgressionBarAtProgress":0,"statHashes":[],"affectsQuality":false,"trueStepIndex":0,"truePropertyIndex":0,"affectsLevel":false}],"exlusiveWithNodes":[402935547,402641165],"randomStartProgressionBarAtProgression":0},{"nodeIndex":2,"nodeHash":402641165,"row":0,"column":0,"prerequisiteNodeIndexes":[],"binaryPairNodeIndex":-1,"autoUnlocks":true,"lastStepRepeats":false,"isRandom":false,"isRandomRepurchasable":false,"steps":[{"stepIndex":0,"nodeStepHash":2787467472,"nodeStepName":"\u30d6\u30fc\u30b9\u30c8","nodeStepDescription":"\u9577\u62bc\u3057\u3067\u52a0\u901f\u3059\u308b\u3002","icon":"\/common\/destiny_content\/icons\/453489e93e5435bbca80a096640615a3.png","damageType":0,"activationRequirement":{"gridLevel":0,"materialRequirementHashes":[]},"canActivateNextStep":false,"nextStepIndex":-1,"isNextStepRandom":false,"perkHashes":[3632688592],"startProgressionBarAtProgress":0,"statHashes":[],"affectsQuality":false,"trueStepIndex":0,"truePropertyIndex":0,"affectsLevel":false}],"exlusiveWithNodes":[402935547,402494132],"randomStartProgressionBarAtProgression":0}],"calcMaxGridLevel":0,"calcProgressToMaxLevel":0}},"definitions":{"destinations":{},"places":{},"activityTypes":{},"items":{},"buckets":{"2025709351":{"bucketHash":2025709351,"bucketName":"\u30d3\u30fc\u30af\u30eb","bucketDescription":"\u5229\u7528\u3067\u304d\u308b\u8d70\u884c\u30d3\u30fc\u30af\u30eb\u3002","scope":0,"category":3,"bucketOrder":11,"bucketIdentifier":"BUCKET_VEHICLE","itemCount":10,"location":1,"hasTransferDestination":true}},"stats":{"360359141":{"statHash":360359141,"statName":"\u8010\u4e45\u529b","statDescription":"\u8010\u4e45\u529b\u304c\u9ad8\u3044\u3068\u3001\u30d3\u30fc\u30af\u30eb\u306f\u3088\u308a\u591a\u304f\u306e\u30c0\u30e1\u30fc\u30b8\u306b\u8010\u3048\u3089\u308c\u308b\u3002","icon":"\/img\/misc\/missing_icon.png","statIdentifier":"STAT_DURABILITY","interpolate":false},"1501155019":{"statHash":1501155019,"statName":"\u30b9\u30d4\u30fc\u30c9","statDescription":"\u5730\u4e0a\u3067\u306e\u30d3\u30fc\u30af\u30eb\u901f\u5ea6\u3002","icon":"\/img\/misc\/missing_icon.png","statIdentifier":"STAT_SPEED","interpolate":false}},"perks":{"3104860955":{"perkHash":3104860955,"displayName":"\u30aa\u30fc\u30d0\u30fc\u30c9\u30e9\u30a4\u30d6","displayDescription":"\u9577\u62bc\u3057\u3067\u7206\u767a\u306e\u5371\u967a\u306e\u3042\u308b\u5927\u5e45\u306a\u52a0\u901f\u3002","displayIcon":"\/img\/misc\/missing_icon.png","isDisplayable":true},"4091143788":{"perkHash":4091143788,"displayName":"\u30d0\u30fc\u30cb\u30a2\u30b9\u30e9\u30b9\u30bf","displayDescription":"\u3068\u3067\u7d20\u65e9\u304f\u6a2a\u306b\u52d5\u304f\u3002","displayIcon":"\/img\/misc\/missing_icon.png","isDisplayable":true},"3632688592":{"perkHash":3632688592,"displayName":"\u30d6\u30fc\u30b9\u30c8","displayDescription":"\u9577\u62bc\u3057\u3067\u52a0\u901f\u3059\u308b\u3002","displayIcon":"\/img\/misc\/missing_icon.png","isDisplayable":true}},"talentGrids":{"2064730451":{"gridHash":2064730451,"maxGridLevel":0,"gridLevelPerColumn":0,"progressionHash":0,"nodes":[{"nodeIndex":0,"nodeHash":402935547,"row":2,"column":0,"prerequisiteNodeIndexes":[],"binaryPairNodeIndex":-1,"autoUnlocks":true,"lastStepRepeats":false,"isRandom":false,"isRandomRepurchasable":false,"steps":[{"stepIndex":0,"nodeStepHash":1458802667,"nodeStepName":"\u30aa\u30fc\u30d0\u30fc\u30c9\u30e9\u30a4\u30d6","nodeStepDescription":"\u9577\u62bc\u3057\u3067\u3001\u81ea\u5206\u306e\u8eab\u4f53\u3092\u591a\u5c11\u5371\u967a\u306b\u3055\u3089\u3059\u4ee3\u308f\u308a\u306b\u52a0\u901f\u3067\u304d\u308b\u3002","icon":"\/common\/destiny_content\/icons\/12028ee57e77dc48dd23821a3a9d8825.png","damageType":0,"activationRequirement":{"gridLevel":0,"materialRequirementHashes":[]},"canActivateNextStep":false,"nextStepIndex":-1,"isNextStepRandom":false,"perkHashes":[3104860955],"startProgressionBarAtProgress":0,"statHashes":[],"affectsQuality":false,"trueStepIndex":0,"truePropertyIndex":0,"affectsLevel":false}],"exlusiveWithNodes":[402494132,402641165],"randomStartProgressionBarAtProgression":0},{"nodeIndex":1,"nodeHash":402494132,"row":1,"column":0,"prerequisiteNodeIndexes":[],"binaryPairNodeIndex":-1,"autoUnlocks":true,"lastStepRepeats":false,"isRandom":false,"isRandomRepurchasable":false,"steps":[{"stepIndex":0,"nodeStepHash":1896096036,"nodeStepName":"\u30b9\u30c8\u30e9\u30d5\u30b9\u30e9\u30b9\u30bf","nodeStepDescription":"\u3068\u3067\u7d20\u65e9\u304f\u6a2a\u306b\u52d5\u304f\u3002","icon":"\/common\/destiny_content\/icons\/1ea15f44a8a5f90c111ebbe7dd43ab85.png","damageType":0,"activationRequirement":{"gridLevel":0,"materialRequirementHashes":[]},"canActivateNextStep":false,"nextStepIndex":-1,"isNextStepRandom":false,"perkHashes":[4091143788],"startProgressionBarAtProgress":0,"statHashes":[],"affectsQuality":false,"trueStepIndex":0,"truePropertyIndex":0,"affectsLevel":false}],"exlusiveWithNodes":[402935547,402641165],"randomStartProgressionBarAtProgression":0},{"nodeIndex":2,"nodeHash":402641165,"row":0,"column":0,"prerequisiteNodeIndexes":[],"binaryPairNodeIndex":-1,"autoUnlocks":true,"lastStepRepeats":false,"isRandom":false,"isRandomRepurchasable":false,"steps":[{"stepIndex":0,"nodeStepHash":2787467472,"nodeStepName":"\u30d6\u30fc\u30b9\u30c8","nodeStepDescription":"\u9577\u62bc\u3057\u3067\u52a0\u901f\u3059\u308b\u3002","icon":"\/common\/destiny_content\/icons\/453489e93e5435bbca80a096640615a3.png","damageType":0,"activationRequirement":{"gridLevel":0,"materialRequirementHashes":[]},"canActivateNextStep":false,"nextStepIndex":-1,"isNextStepRandom":false,"perkHashes":[3632688592],"startProgressionBarAtProgress":0,"statHashes":[],"affectsQuality":false,"trueStepIndex":0,"truePropertyIndex":0,"affectsLevel":false}],"exlusiveWithNodes":[402935547,402494132],"randomStartProgressionBarAtProgression":0}],"calcMaxGridLevel":0,"calcProgressToMaxLevel":0}},"statGroups":{"2025709351":{"statGroupHash":2025709351,"maximumValue":10,"uiPosition":0,"scaledStats":[{"statHash":1501155019,"maximumValue":10,"displayAsNumeric":false,"displayInterpolation":[{"value":0,"weight":0},{"value":100,"weight":100}]}],"overrides":{}}},"progressionMappings":{},"sources":{},"progressions":{},"materialRequirements":{},"factions":{},"events":{},"vendorSummaries":{},"activityBundles":{},"books":{}}}