{"data":{"requestedId":152628833,"inventoryItem":{"itemHash":152628833,"itemName":"Corrective Measure","itemDescription":"It breaks the rules of reality as ruthlessly as it shatters your foes.","icon":"\/common\/destiny_content\/icons\/34d5d4f4286c7b4e4ef66f39c10f0238.jpg","secondaryIcon":"\/img\/misc\/missing_icon.png","actionName":"Dismantle","tierTypeName":"Legendary","tierType":5,"itemTypeName":"Machine Gun","bucketTypeHash":953998645,"primaryBaseStatHash":368428387,"stats":{"368428387":{"statHash":368428387,"value":248,"minimum":248,"maximum":300},"3555269338":{"statHash":3555269338,"value":15,"minimum":15,"maximum":15},"4284893193":{"statHash":4284893193,"value":88,"minimum":88,"maximum":88},"4043523819":{"statHash":4043523819,"value":27,"minimum":27,"maximum":33},"1240592695":{"statHash":1240592695,"value":18,"minimum":18,"maximum":24},"155624089":{"statHash":155624089,"value":50,"minimum":35,"maximum":94},"3871231066":{"statHash":3871231066,"value":58,"minimum":58,"maximum":100},"4188031367":{"statHash":4188031367,"value":39,"minimum":39,"maximum":39},"1931675084":{"statHash":1931675084,"value":20,"minimum":20,"maximum":100},"943549884":{"statHash":943549884,"value":55,"minimum":50,"maximum":55},"1345609583":{"statHash":1345609583,"value":69,"minimum":69,"maximum":69},"2715839340":{"statHash":2715839340,"value":71,"minimum":71,"maximum":71}},"perkHashes":[3274301702],"specialItemType":0,"talentGridHash":3782993714,"equippingBlock":{"weaponSandboxPatternIndex":17,"gearArtArrangementIndex":1413,"defaultDyes":[],"lockedDyes":[{"channelHash":1667433279,"dyeHash":3165550597},{"channelHash":1667433278,"dyeHash":3570620350}],"customDyes":[],"customDyeExpression":{"steps":[]},"weaponPatternHash":2076731175},"hasGeometry":true,"statGroupHash":1232481893,"itemLevels":[0],"qualityLevel":60,"rewardItemHash":0,"values":{},"itemType":3,"itemSubType":8,"classType":3,"nonTransferrable":false,"exclusive":0,"maxStackSize":1},"talentGrid":{"gridHash":3782993714,"maxGridLevel":0,"gridLevelPerColumn":0,"progressionHash":1296042811,"nodes":[{"nodeIndex":0,"nodeHash":4076480290,"row":0,"column":5,"prerequisiteNodeIndexes":[],"binaryPairNodeIndex":-1,"autoUnlocks":false,"lastStepRepeats":false,"isRandom":false,"isRandomRepurchasable":false,"steps":[{"stepIndex":0,"nodeStepHash":3110691286,"nodeStepName":"Surplus","nodeStepDescription":"Expect to find more ammo for this weapon.","interactionDescription":"Upgrade","icon":"\/common\/destiny_content\/icons\/d15829c40438313bb8c3226d3763e097.png","damageType":0,"activationRequirement":{"gridLevel":6,"materialRequirementHashes":[659267613]},"canActivateNextStep":false,"nextStepIndex":-1,"isNextStepRandom":false,"perkHashes":[3317503477],"startProgressionBarAtProgress":52500,"statHashes":[],"affectsQuality":false,"stepGroups":{"weaponPerformance":512,"impactEffects":0,"guardianAttributes":0,"lightAbilities":0,"damageTypes":0},"trueStepIndex":0,"truePropertyIndex":0,"affectsLevel":false}],"exlusiveWithNodes":[],"randomStartProgressionBarAtProgression":0},{"nodeIndex":1,"nodeHash":402641165,"row":0,"column":0,"prerequisiteNodeIndexes":[],"binaryPairNodeIndex":-1,"autoUnlocks":true,"lastStepRepeats":false,"isRandom":false,"isRandomRepurchasable":false,"steps":[{"stepIndex":0,"nodeStepHash":4134271514,"nodeStepName":"Void Damage","nodeStepDescription":"This weapon causes Void Damage.","interactionDescription":"Reroll","icon":"\/common\/destiny_content\/icons\/bc527dbbeed646129dbda1a29f719fc3.png","damageType":4,"activationRequirement":{"gridLevel":0,"materialRequirementHashes":[]},"canActivateNextStep":false,"nextStepIndex":-1,"isNextStepRandom":false,"perkHashes":[3614988247],"startProgressionBarAtProgress":0,"statHashes":[],"affectsQuality":false,"stepGroups":{"weaponPerformance":0,"impactEffects":0,"guardianAttributes":0,"lightAbilities":0,"damageTypes":8},"trueStepIndex":0,"truePropertyIndex":0,"affectsLevel":false}],"exlusiveWithNodes":[],"randomStartProgressionBarAtProgression":0},{"nodeIndex":2,"nodeHash":1144665524,"row":0,"column":3,"prerequisiteNodeIndexes":[],"binaryPairNodeIndex":-1,"autoUnlocks":false,"lastStepRepeats":false,"isRandom":false,"isRandomRepurchasable":false,"steps":[{"stepIndex":0,"nodeStepHash":491986635,"nodeStepName":"Upgrade Damage","nodeStepDescription":"Increases Attack Power, allowing this weapon to cause more damage.","interactionDescription":"Upgrade","icon":"\/common\/destiny_content\/icons\/2c564a7f220855661066d6a308940940.png","damageType":0,"activationRequirement":{"gridLevel":4,"materialRequirementHashes":[1600885976,1600885977,1600885978,1600885979]},"canActivateNextStep":false,"nextStepIndex":-1,"isNextStepRandom":false,"perkHashes":[],"startProgressionBarAtProgress":7500,"statHashes":[],"affectsQuality":true,"trueStepIndex":0,"truePropertyIndex":0,"affectsLevel":false}],"exlusiveWithNodes":[],"randomStartProgressionBarAtProgression":0},{"nodeIndex":3,"nodeHash":3452924987,"row":0,"column":2,"prerequisiteNodeIndexes":[],"binaryPairNodeIndex":-1,"autoUnlocks":false,"lastStepRepeats":false,"isRandom":false,"isRandomRepurchasable":false,"steps":[{"stepIndex":0,"nodeStepHash":2001784245,"nodeStepName":"Persistence","nodeStepDescription":"This weapon grows more accurate the longer it is fired.","interactionDescription":"Reroll","icon":"\/common\/destiny_content\/icons\/258faac56b43d674967222a5d68d2adb.png","damageType":0,"activationRequirement":{"gridLevel":2,"materialRequirementHashes":[659267613]},"canActivateNextStep":false,"nextStepIndex":-1,"isNextStepRandom":false,"perkHashes":[808857588],"startProgressionBarAtProgress":0,"statHashes":[],"affectsQuality":false,"stepGroups":{"weaponPerformance":4,"impactEffects":0,"guardianAttributes":0,"lightAbilities":0,"damageTypes":0},"trueStepIndex":0,"truePropertyIndex":0,"affectsLevel":false}],"exlusiveWithNodes":[],"randomStartProgressionBarAtProgression":0},{"nodeIndex":4,"nodeHash":1173110174,"row":1,"column":6,"prerequisiteNodeIndexes":[],"binaryPairNodeIndex":-1,"autoUnlocks":false,"lastStepRepeats":false,"isRandom":false,"isRandomRepurchasable":false,"steps":[{"stepIndex":0,"nodeStepHash":3984344998,"nodeStepName":"Oracle Disruptor","nodeStepDescription":"This weapon deals bonus damage to Oracles in the Vault of Glass.","interactionDescription":"Reroll","icon":"\/common\/destiny_content\/icons\/66920e5fa295545d40a573bf9f6d7690.png","damageType":0,"activationRequirement":{"gridLevel":9,"materialRequirementHashes":[659267613]},"canActivateNextStep":false,"nextStepIndex":-1,"isNextStepRandom":false,"perkHashes":[3076531258],"startProgressionBarAtProgress":97500,"statHashes":[],"affectsQuality":false,"stepGroups":{"weaponPerformance":2,"impactEffects":0,"guardianAttributes":0,"lightAbilities":0,"damageTypes":0},"trueStepIndex":0,"truePropertyIndex":0,"affectsLevel":false}],"exlusiveWithNodes":[],"randomStartProgressionBarAtProgression":0},{"nodeIndex":5,"nodeHash":486779184,"row":0,"column":7,"prerequisiteNodeIndexes":[],"binaryPairNodeIndex":-1,"autoUnlocks":false,"lastStepRepeats":false,"isRandom":false,"isRandomRepurchasable":false,"steps":[{"stepIndex":0,"nodeStepHash":1277492283,"nodeStepName":"Upgrade Damage","nodeStepDescription":"Increases Attack Power, allowing this weapon to cause more damage.","interactionDescription":"Upgrade","icon":"\/common\/destiny_content\/icons\/2c564a7f220855661066d6a308940940.png","damageType":0,"activationRequirement":{"gridLevel":9,"materialRequirementHashes":[670361628,670361629,670361630,670361631]},"canActivateNextStep":false,"nextStepIndex":-1,"isNextStepRandom":false,"perkHashes":[],"startProgressionBarAtProgress":97500,"statHashes":[],"affectsQuality":true,"trueStepIndex":0,"truePropertyIndex":0,"affectsLevel":false}],"exlusiveWithNodes":[],"randomStartProgressionBarAtProgression":0},{"nodeIndex":6,"nodeHash":1560693961,"row":1,"column":7,"prerequisiteNodeIndexes":[],"binaryPairNodeIndex":-1,"autoUnlocks":false,"lastStepRepeats":false,"isRandom":false,"isRandomRepurchasable":false,"steps":[{"stepIndex":0,"nodeStepHash":4227382570,"nodeStepName":"Upgrade Damage","nodeStepDescription":"Increases Attack Power, allowing this weapon to cause more damage.","interactionDescription":"Upgrade","icon":"\/common\/destiny_content\/icons\/2c564a7f220855661066d6a308940940.png","damageType":0,"activationRequirement":{"gridLevel":10,"materialRequirementHashes":[670361628,670361629,670361630,670361631]},"canActivateNextStep":false,"nextStepIndex":-1,"isNextStepRandom":false,"perkHashes":[],"startProgressionBarAtProgress":112500,"statHashes":[],"affectsQuality":true,"trueStepIndex":0,"truePropertyIndex":0,"affectsLevel":false}],"exlusiveWithNodes":[],"randomStartProgressionBarAtProgression":0},{"nodeIndex":7,"nodeHash":1560841054,"row":2,"column":7,"prerequisiteNodeIndexes":[],"binaryPairNodeIndex":-1,"autoUnlocks":false,"lastStepRepeats":false,"isRandom":false,"isRandomRepurchasable":false,"steps":[{"stepIndex":0,"nodeStepHash":2882305561,"nodeStepName":"Upgrade Damage","nodeStepDescription":"Increases Attack Power, allowing this weapon to cause more damage.","interactionDescription":"Upgrade","icon":"\/common\/destiny_content\/icons\/2c564a7f220855661066d6a308940940.png","damageType":0,"activationRequirement":{"gridLevel":11,"materialRequirementHashes":[670361628,670361629,670361630,670361631]},"canActivateNextStep":false,"nextStepIndex":-1,"isNextStepRandom":false,"perkHashes":[],"startProgressionBarAtProgress":127500,"statHashes":[],"affectsQuality":true,"trueStepIndex":0,"truePropertyIndex":0,"affectsLevel":false}],"exlusiveWithNodes":[],"randomStartProgressionBarAtProgression":0},{"nodeIndex":8,"nodeHash":3872169477,"row":2,"column":4,"prerequisiteNodeIndexes":[],"binaryPairNodeIndex":-1,"autoUnlocks":false,"lastStepRepeats":false,"isRandom":false,"isRandomRepurchasable":false,"steps":[{"stepIndex":0,"nodeStepHash":3241612944,"nodeStepName":"Field Scout","nodeStepDescription":"Maximum Ammo capacity.","interactionDescription":"Upgrade","icon":"\/common\/destiny_content\/icons\/0aeba7e8935ea9f58dd314faf4fc6018.png","damageType":0,"activationRequirement":{"gridLevel":7,"materialRequirementHashes":[659267613]},"canActivateNextStep":false,"nextStepIndex":-1,"isNextStepRandom":false,"perkHashes":[],"startProgressionBarAtProgress":67500,"statHashes":[3871231066,1931675084],"affectsQuality":false,"stepGroups":{"weaponPerformance":512,"impactEffects":0,"guardianAttributes":0,"lightAbilities":0,"damageTypes":0},"trueStepIndex":0,"truePropertyIndex":0,"affectsLevel":false}],"exlusiveWithNodes":[3359939809,2947148901],"randomStartProgressionBarAtProgression":0},{"nodeIndex":9,"nodeHash":3359939809,"row":1,"column":4,"prerequisiteNodeIndexes":[],"binaryPairNodeIndex":-1,"autoUnlocks":false,"lastStepRepeats":false,"isRandom":false,"isRandomRepurchasable":false,"steps":[{"stepIndex":0,"nodeStepHash":2364201573,"nodeStepName":"Perfect Balance","nodeStepDescription":"This weapon has extremely low recoil.","interactionDescription":"Upgrade","icon":"\/common\/destiny_content\/icons\/c3e046769007f47035b3e0abb2e8f92e.png","damageType":0,"activationRequirement":{"gridLevel":6,"materialRequirementHashes":[659267613]},"canActivateNextStep":false,"nextStepIndex":-1,"isNextStepRandom":false,"perkHashes":[],"startProgressionBarAtProgress":52500,"statHashes":[155624089],"affectsQuality":false,"stepGroups":{"weaponPerformance":32,"impactEffects":0,"guardianAttributes":0,"lightAbilities":0,"damageTypes":0},"trueStepIndex":0,"truePropertyIndex":0,"affectsLevel":false}],"exlusiveWithNodes":[3872169477,2947148901],"randomStartProgressionBarAtProgression":0},{"nodeIndex":10,"nodeHash":2947148901,"row":0,"column":4,"prerequisiteNodeIndexes":[],"binaryPairNodeIndex":-1,"autoUnlocks":false,"lastStepRepeats":false,"isRandom":false,"isRandomRepurchasable":false,"steps":[{"stepIndex":0,"nodeStepHash":4164836131,"nodeStepName":"Armor Piercing Rounds","nodeStepDescription":"These iridium-core rounds overpenetrate targets.\nTheir mass slows down weapon handling.","interactionDescription":"Upgrade","icon":"\/common\/destiny_content\/icons\/53310f5e62b6748ffd30a99e5d06e162.png","damageType":0,"activationRequirement":{"gridLevel":5,"materialRequirementHashes":[659267613]},"canActivateNextStep":false,"nextStepIndex":-1,"isNextStepRandom":false,"perkHashes":[3020342826],"startProgressionBarAtProgress":37500,"statHashes":[4043523819,943549884],"affectsQuality":false,"stepGroups":{"weaponPerformance":64,"impactEffects":0,"guardianAttributes":0,"lightAbilities":0,"damageTypes":0},"trueStepIndex":0,"truePropertyIndex":0,"affectsLevel":false}],"exlusiveWithNodes":[3872169477,3359939809],"randomStartProgressionBarAtProgression":0},{"nodeIndex":11,"nodeHash":312682976,"row":1,"column":1,"prerequisiteNodeIndexes":[],"binaryPairNodeIndex":-1,"autoUnlocks":false,"lastStepRepeats":false,"isRandom":false,"isRandomRepurchasable":false,"steps":[{"stepIndex":0,"nodeStepHash":2187318329,"nodeStepName":"Accurized Ballistics","nodeStepDescription":"More range and Impact. \nIncreased recoil.","interactionDescription":"Upgrade","icon":"\/common\/destiny_content\/icons\/8bffa8be796e8b0b27add34529a7d1d7.png","damageType":0,"activationRequirement":{"gridLevel":3,"materialRequirementHashes":[]},"canActivateNextStep":false,"nextStepIndex":-1,"isNextStepRandom":false,"perkHashes":[2868044506],"startProgressionBarAtProgress":7500,"statHashes":[1240592695,4043523819,155624089],"affectsQuality":false,"stepGroups":{"weaponPerformance":40,"impactEffects":0,"guardianAttributes":0,"lightAbilities":0,"damageTypes":0},"trueStepIndex":0,"truePropertyIndex":0,"affectsLevel":false}],"exlusiveWithNodes":[452419628,1503756812],"randomStartProgressionBarAtProgression":0},{"nodeIndex":12,"nodeHash":452419628,"row":0,"column":1,"prerequisiteNodeIndexes":[],"binaryPairNodeIndex":-1,"autoUnlocks":true,"lastStepRepeats":false,"isRandom":false,"isRandomRepurchasable":false,"steps":[{"stepIndex":0,"nodeStepHash":3532395338,"nodeStepName":"Soft Ballistics","nodeStepDescription":"Less recoil. \nPenalty to Impact.","interactionDescription":"Upgrade","icon":"\/common\/destiny_content\/icons\/4f26206cdc6fd31e0cdfe6b24ac2689c.png","damageType":0,"activationRequirement":{"gridLevel":0,"materialRequirementHashes":[]},"canActivateNextStep":false,"nextStepIndex":-1,"isNextStepRandom":false,"perkHashes":[2272440440],"startProgressionBarAtProgress":0,"statHashes":[4043523819,155624089],"affectsQuality":false,"stepGroups":{"weaponPerformance":32,"impactEffects":0,"guardianAttributes":0,"lightAbilities":0,"damageTypes":0},"trueStepIndex":0,"truePropertyIndex":0,"affectsLevel":false}],"exlusiveWithNodes":[312682976,1503756812],"randomStartProgressionBarAtProgression":0},{"nodeIndex":13,"nodeHash":1503756812,"row":2,"column":1,"prerequisiteNodeIndexes":[],"binaryPairNodeIndex":-1,"autoUnlocks":false,"lastStepRepeats":false,"isRandom":false,"isRandomRepurchasable":false,"steps":[{"stepIndex":0,"nodeStepHash":842241320,"nodeStepName":"Field Choke","nodeStepDescription":"More range and Impact. \nIncreased recoil.","interactionDescription":"Upgrade","icon":"\/common\/destiny_content\/icons\/2f6f4f9465d393f760f7e7d4fb9b3806.png","damageType":0,"activationRequirement":{"gridLevel":4,"materialRequirementHashes":[]},"canActivateNextStep":false,"nextStepIndex":-1,"isNextStepRandom":false,"perkHashes":[2868044506],"startProgressionBarAtProgress":22500,"statHashes":[1240592695,4043523819,155624089],"affectsQuality":false,"stepGroups":{"weaponPerformance":40,"impactEffects":0,"guardianAttributes":0,"lightAbilities":0,"damageTypes":0},"trueStepIndex":0,"truePropertyIndex":0,"affectsLevel":false}],"exlusiveWithNodes":[312682976,452419628],"randomStartProgressionBarAtProgression":0},{"nodeIndex":14,"nodeHash":99489719,"row":0,"column":6,"prerequisiteNodeIndexes":[],"binaryPairNodeIndex":-1,"autoUnlocks":false,"lastStepRepeats":false,"isRandom":false,"isRandomRepurchasable":false,"steps":[{"stepIndex":0,"nodeStepHash":491986635,"nodeStepName":"Upgrade Damage","nodeStepDescription":"Increases Attack Power, allowing this weapon to cause more damage.","interactionDescription":"Upgrade","icon":"\/common\/destiny_content\/icons\/2c564a7f220855661066d6a308940940.png","damageType":0,"activationRequirement":{"gridLevel":8,"materialRequirementHashes":[3021864743,3021864742,3021864741,3021864740]},"canActivateNextStep":false,"nextStepIndex":-1,"isNextStepRandom":false,"perkHashes":[],"startProgressionBarAtProgress":67500,"statHashes":[],"affectsQuality":true,"trueStepIndex":0,"truePropertyIndex":0,"affectsLevel":false}],"exlusiveWithNodes":[],"randomStartProgressionBarAtProgression":0},{"nodeIndex":15,"nodeHash":2658293415,"row":0,"column":-2,"prerequisiteNodeIndexes":[],"binaryPairNodeIndex":-1,"autoUnlocks":false,"lastStepRepeats":false,"isRandom":false,"isRandomRepurchasable":false,"steps":[{"stepIndex":0,"nodeStepHash":3809873841,"icon":"\/img\/misc\/missing_icon.png","damageType":0,"activationRequirement":{"gridLevel":0,"materialRequirementHashes":[]},"canActivateNextStep":false,"nextStepIndex":-1,"isNextStepRandom":false,"perkHashes":[646250337],"startProgressionBarAtProgress":0,"statHashes":[],"affectsQuality":false,"trueStepIndex":0,"truePropertyIndex":0,"affectsLevel":false}],"exlusiveWithNodes":[],"randomStartProgressionBarAtProgression":0}],"calcMaxGridLevel":0,"calcProgressToMaxLevel":0}},"definitions":{"destinations":{},"places":{},"activityTypes":{},"items":{},"buckets":{"953998645":{"bucketHash":953998645,"bucketName":"Heavy Weapons","bucketDescription":"Machine guns and rocket launchers.","scope":0,"category":3,"bucketOrder":4,"bucketIdentifier":"BUCKET_HEAVY_WEAPON","itemCount":10,"location":1,"hasTransferDestination":true}},"stats":{"368428387":{"statHash":368428387,"statName":"Attack","statDescription":"Higher Attack allows your weapons to damage higher-level opponents.","icon":"\/img\/misc\/missing_icon.png","statIdentifier":"STAT_DAMAGE","interpolate":false},"3555269338":{"statHash":3555269338,"statName":"Optics","statDescription":"Optical Zoom Multiplier","icon":"\/img\/misc\/missing_icon.png","statIdentifier":"STAT_OPTICS","interpolate":false},"4284893193":{"statHash":4284893193,"statName":"Rate of Fire","statDescription":"The number of shots per minute this weapon can fire.","icon":"\/img\/misc\/missing_icon.png","statIdentifier":"STAT_RATE_OF_FIRE","interpolate":false},"4043523819":{"statHash":4043523819,"statName":"Impact","statDescription":"Increases the damage inflicted by each round.","icon":"\/img\/misc\/missing_icon.png","statIdentifier":"STAT_BASE_DAMAGE","interpolate":false},"1240592695":{"statHash":1240592695,"statName":"Range","statDescription":"Increases the effective range of this weapon.","icon":"\/img\/misc\/missing_icon.png","statIdentifier":"STAT_RANGE","interpolate":false},"155624089":{"statHash":155624089,"statName":"Stability","statDescription":"Decreases weapon recoil when fired continuously.","icon":"\/img\/misc\/missing_icon.png","statIdentifier":"STAT_STABILITY","interpolate":false},"3871231066":{"statHash":3871231066,"statName":"Magazine","statDescription":"The number of shots which can be fired before reloading.","icon":"\/img\/misc\/missing_icon.png","statIdentifier":"STAT_MAGAZINE_SIZE","interpolate":false},"4188031367":{"statHash":4188031367,"statName":"Reload","statDescription":"Decreases the time it takes to reload this weapon.","icon":"\/img\/misc\/missing_icon.png","statIdentifier":"STAT_RELOAD","interpolate":false},"1931675084":{"statHash":1931675084,"statName":"Inventory Size","statDescription":"How much space the weapon occupies in the inventory.","icon":"\/img\/misc\/missing_icon.png","statIdentifier":"STAT_INVENTORY_SIZE","interpolate":false},"943549884":{"statHash":943549884,"statName":"Equip Speed","statDescription":"The speed with which the weapon can be readied and aimed.","icon":"\/img\/misc\/missing_icon.png","statIdentifier":"STAT_EQUIP_SPEED","interpolate":false},"1345609583":{"statHash":1345609583,"statName":"Aim assistance","statDescription":"The weapon's ability to augment your aim.","icon":"\/img\/misc\/missing_icon.png","statIdentifier":"STAT_AIM_ASSISTANCE","interpolate":false},"2715839340":{"statHash":2715839340,"statName":"Recoil direction","statDescription":"The weapon's tendency to move while firing.","icon":"\/img\/misc\/missing_icon.png","statIdentifier":"STAT_RECOIL_DIRECTION","interpolate":false}},"perks":{"3274301702":{"perkHash":3274301702,"displayIcon":"\/img\/misc\/missing_icon.png","isDisplayable":false},"3317503477":{"perkHash":3317503477,"displayName":"Surplus","displayDescription":"Expect to find more ammo for this weapon.","displayIcon":"\/img\/misc\/missing_icon.png","isDisplayable":true,"perkGroups":{"weaponPerformance":512,"impactEffects":0,"guardianAttributes":0,"lightAbilities":0,"damageTypes":0}},"3614988247":{"perkHash":3614988247,"displayIcon":"\/img\/misc\/missing_icon.png","perkIdentifier":"PERK_VOID_DAMAGE","isDisplayable":false,"perkGroups":{"weaponPerformance":0,"impactEffects":0,"guardianAttributes":0,"lightAbilities":0,"damageTypes":8}},"808857588":{"perkHash":808857588,"displayName":"Persistence","displayDescription":"This weapon grows more accurate the longer it is fired.","displayIcon":"\/img\/misc\/missing_icon.png","isDisplayable":true,"perkGroups":{"weaponPerformance":4,"impactEffects":0,"guardianAttributes":0,"lightAbilities":0,"damageTypes":0}},"3076531258":{"perkHash":3076531258,"displayIcon":"\/img\/misc\/missing_icon.png","isDisplayable":false,"perkGroups":{"weaponPerformance":2,"impactEffects":0,"guardianAttributes":0,"lightAbilities":0,"damageTypes":0}},"3020342826":{"perkHash":3020342826,"displayIcon":"\/img\/misc\/missing_icon.png","isDisplayable":false},"2868044506":{"perkHash":2868044506,"displayIcon":"\/img\/misc\/missing_icon.png","isDisplayable":false},"2272440440":{"perkHash":2272440440,"displayIcon":"\/img\/misc\/missing_icon.png","isDisplayable":false},"646250337":{"perkHash":646250337,"displayIcon":"\/img\/misc\/missing_icon.png","isDisplayable":false}},"talentGrids":{"3782993714":{"gridHash":3782993714,"maxGridLevel":0,"gridLevelPerColumn":0,"progressionHash":1296042811,"nodes":[{"nodeIndex":0,"nodeHash":4076480290,"row":0,"column":5,"prerequisiteNodeIndexes":[],"binaryPairNodeIndex":-1,"autoUnlocks":false,"lastStepRepeats":false,"isRandom":false,"isRandomRepurchasable":false,"steps":[{"stepIndex":0,"nodeStepHash":3110691286,"nodeStepName":"Surplus","nodeStepDescription":"Expect to find more ammo for this weapon.","interactionDescription":"Upgrade","icon":"\/common\/destiny_content\/icons\/d15829c40438313bb8c3226d3763e097.png","damageType":0,"activationRequirement":{"gridLevel":6,"materialRequirementHashes":[659267613]},"canActivateNextStep":false,"nextStepIndex":-1,"isNextStepRandom":false,"perkHashes":[3317503477],"startProgressionBarAtProgress":52500,"statHashes":[],"affectsQuality":false,"stepGroups":{"weaponPerformance":512,"impactEffects":0,"guardianAttributes":0,"lightAbilities":0,"damageTypes":0},"trueStepIndex":0,"truePropertyIndex":0,"affectsLevel":false}],"exlusiveWithNodes":[],"randomStartProgressionBarAtProgression":0},{"nodeIndex":1,"nodeHash":402641165,"row":0,"column":0,"prerequisiteNodeIndexes":[],"binaryPairNodeIndex":-1,"autoUnlocks":true,"lastStepRepeats":false,"isRandom":false,"isRandomRepurchasable":false,"steps":[{"stepIndex":0,"nodeStepHash":4134271514,"nodeStepName":"Void Damage","nodeStepDescription":"This weapon causes Void Damage.","interactionDescription":"Reroll","icon":"\/common\/destiny_content\/icons\/bc527dbbeed646129dbda1a29f719fc3.png","damageType":4,"activationRequirement":{"gridLevel":0,"materialRequirementHashes":[]},"canActivateNextStep":false,"nextStepIndex":-1,"isNextStepRandom":false,"perkHashes":[3614988247],"startProgressionBarAtProgress":0,"statHashes":[],"affectsQuality":false,"stepGroups":{"weaponPerformance":0,"impactEffects":0,"guardianAttributes":0,"lightAbilities":0,"damageTypes":8},"trueStepIndex":0,"truePropertyIndex":0,"affectsLevel":false}],"exlusiveWithNodes":[],"randomStartProgressionBarAtProgression":0},{"nodeIndex":2,"nodeHash":1144665524,"row":0,"column":3,"prerequisiteNodeIndexes":[],"binaryPairNodeIndex":-1,"autoUnlocks":false,"lastStepRepeats":false,"isRandom":false,"isRandomRepurchasable":false,"steps":[{"stepIndex":0,"nodeStepHash":491986635,"nodeStepName":"Upgrade Damage","nodeStepDescription":"Increases Attack Power, allowing this weapon to cause more damage.","interactionDescription":"Upgrade","icon":"\/common\/destiny_content\/icons\/2c564a7f220855661066d6a308940940.png","damageType":0,"activationRequirement":{"gridLevel":4,"materialRequirementHashes":[1600885976,1600885977,1600885978,1600885979]},"canActivateNextStep":false,"nextStepIndex":-1,"isNextStepRandom":false,"perkHashes":[],"startProgressionBarAtProgress":7500,"statHashes":[],"affectsQuality":true,"trueStepIndex":0,"truePropertyIndex":0,"affectsLevel":false}],"exlusiveWithNodes":[],"randomStartProgressionBarAtProgression":0},{"nodeIndex":3,"nodeHash":3452924987,"row":0,"column":2,"prerequisiteNodeIndexes":[],"binaryPairNodeIndex":-1,"autoUnlocks":false,"lastStepRepeats":false,"isRandom":false,"isRandomRepurchasable":false,"steps":[{"stepIndex":0,"nodeStepHash":2001784245,"nodeStepName":"Persistence","nodeStepDescription":"This weapon grows more accurate the longer it is fired.","interactionDescription":"Reroll","icon":"\/common\/destiny_content\/icons\/258faac56b43d674967222a5d68d2adb.png","damageType":0,"activationRequirement":{"gridLevel":2,"materialRequirementHashes":[659267613]},"canActivateNextStep":false,"nextStepIndex":-1,"isNextStepRandom":false,"perkHashes":[808857588],"startProgressionBarAtProgress":0,"statHashes":[],"affectsQuality":false,"stepGroups":{"weaponPerformance":4,"impactEffects":0,"guardianAttributes":0,"lightAbilities":0,"damageTypes":0},"trueStepIndex":0,"truePropertyIndex":0,"affectsLevel":false}],"exlusiveWithNodes":[],"randomStartProgressionBarAtProgression":0},{"nodeIndex":4,"nodeHash":1173110174,"row":1,"column":6,"prerequisiteNodeIndexes":[],"binaryPairNodeIndex":-1,"autoUnlocks":false,"lastStepRepeats":false,"isRandom":false,"isRandomRepurchasable":false,"steps":[{"stepIndex":0,"nodeStepHash":3984344998,"nodeStepName":"Oracle Disruptor","nodeStepDescription":"This weapon deals bonus damage to Oracles in the Vault of Glass.","interactionDescription":"Reroll","icon":"\/common\/destiny_content\/icons\/66920e5fa295545d40a573bf9f6d7690.png","damageType":0,"activationRequirement":{"gridLevel":9,"materialRequirementHashes":[659267613]},"canActivateNextStep":false,"nextStepIndex":-1,"isNextStepRandom":false,"perkHashes":[3076531258],"startProgressionBarAtProgress":97500,"statHashes":[],"affectsQuality":false,"stepGroups":{"weaponPerformance":2,"impactEffects":0,"guardianAttributes":0,"lightAbilities":0,"damageTypes":0},"trueStepIndex":0,"truePropertyIndex":0,"affectsLevel":false}],"exlusiveWithNodes":[],"randomStartProgressionBarAtProgression":0},{"nodeIndex":5,"nodeHash":486779184,"row":0,"column":7,"prerequisiteNodeIndexes":[],"binaryPairNodeIndex":-1,"autoUnlocks":false,"lastStepRepeats":false,"isRandom":false,"isRandomRepurchasable":false,"steps":[{"stepIndex":0,"nodeStepHash":1277492283,"nodeStepName":"Upgrade Damage","nodeStepDescription":"Increases Attack Power, allowing this weapon to cause more damage.","interactionDescription":"Upgrade","icon":"\/common\/destiny_content\/icons\/2c564a7f220855661066d6a308940940.png","damageType":0,"activationRequirement":{"gridLevel":9,"materialRequirementHashes":[670361628,670361629,670361630,670361631]},"canActivateNextStep":false,"nextStepIndex":-1,"isNextStepRandom":false,"perkHashes":[],"startProgressionBarAtProgress":97500,"statHashes":[],"affectsQuality":true,"trueStepIndex":0,"truePropertyIndex":0,"affectsLevel":false}],"exlusiveWithNodes":[],"randomStartProgressionBarAtProgression":0},{"nodeIndex":6,"nodeHash":1560693961,"row":1,"column":7,"prerequisiteNodeIndexes":[],"binaryPairNodeIndex":-1,"autoUnlocks":false,"lastStepRepeats":false,"isRandom":false,"isRandomRepurchasable":false,"steps":[{"stepIndex":0,"nodeStepHash":4227382570,"nodeStepName":"Upgrade Damage","nodeStepDescription":"Increases Attack Power, allowing this weapon to cause more damage.","interactionDescription":"Upgrade","icon":"\/common\/destiny_content\/icons\/2c564a7f220855661066d6a308940940.png","damageType":0,"activationRequirement":{"gridLevel":10,"materialRequirementHashes":[670361628,670361629,670361630,670361631]},"canActivateNextStep":false,"nextStepIndex":-1,"isNextStepRandom":false,"perkHashes":[],"startProgressionBarAtProgress":112500,"statHashes":[],"affectsQuality":true,"trueStepIndex":0,"truePropertyIndex":0,"affectsLevel":false}],"exlusiveWithNodes":[],"randomStartProgressionBarAtProgression":0},{"nodeIndex":7,"nodeHash":1560841054,"row":2,"column":7,"prerequisiteNodeIndexes":[],"binaryPairNodeIndex":-1,"autoUnlocks":false,"lastStepRepeats":false,"isRandom":false,"isRandomRepurchasable":false,"steps":[{"stepIndex":0,"nodeStepHash":2882305561,"nodeStepName":"Upgrade Damage","nodeStepDescription":"Increases Attack Power, allowing this weapon to cause more damage.","interactionDescription":"Upgrade","icon":"\/common\/destiny_content\/icons\/2c564a7f220855661066d6a308940940.png","damageType":0,"activationRequirement":{"gridLevel":11,"materialRequirementHashes":[670361628,670361629,670361630,670361631]},"canActivateNextStep":false,"nextStepIndex":-1,"isNextStepRandom":false,"perkHashes":[],"startProgressionBarAtProgress":127500,"statHashes":[],"affectsQuality":true,"trueStepIndex":0,"truePropertyIndex":0,"affectsLevel":false}],"exlusiveWithNodes":[],"randomStartProgressionBarAtProgression":0},{"nodeIndex":8,"nodeHash":3872169477,"row":2,"column":4,"prerequisiteNodeIndexes":[],"binaryPairNodeIndex":-1,"autoUnlocks":false,"lastStepRepeats":false,"isRandom":false,"isRandomRepurchasable":false,"steps":[{"stepIndex":0,"nodeStepHash":3241612944,"nodeStepName":"Field Scout","nodeStepDescription":"Maximum Ammo capacity.","interactionDescription":"Upgrade","icon":"\/common\/destiny_content\/icons\/0aeba7e8935ea9f58dd314faf4fc6018.png","damageType":0,"activationRequirement":{"gridLevel":7,"materialRequirementHashes":[659267613]},"canActivateNextStep":false,"nextStepIndex":-1,"isNextStepRandom":false,"perkHashes":[],"startProgressionBarAtProgress":67500,"statHashes":[3871231066,1931675084],"affectsQuality":false,"stepGroups":{"weaponPerformance":512,"impactEffects":0,"guardianAttributes":0,"lightAbilities":0,"damageTypes":0},"trueStepIndex":0,"truePropertyIndex":0,"affectsLevel":false}],"exlusiveWithNodes":[3359939809,2947148901],"randomStartProgressionBarAtProgression":0},{"nodeIndex":9,"nodeHash":3359939809,"row":1,"column":4,"prerequisiteNodeIndexes":[],"binaryPairNodeIndex":-1,"autoUnlocks":false,"lastStepRepeats":false,"isRandom":false,"isRandomRepurchasable":false,"steps":[{"stepIndex":0,"nodeStepHash":2364201573,"nodeStepName":"Perfect Balance","nodeStepDescription":"This weapon has extremely low recoil.","interactionDescription":"Upgrade","icon":"\/common\/destiny_content\/icons\/c3e046769007f47035b3e0abb2e8f92e.png","damageType":0,"activationRequirement":{"gridLevel":6,"materialRequirementHashes":[659267613]},"canActivateNextStep":false,"nextStepIndex":-1,"isNextStepRandom":false,"perkHashes":[],"startProgressionBarAtProgress":52500,"statHashes":[155624089],"affectsQuality":false,"stepGroups":{"weaponPerformance":32,"impactEffects":0,"guardianAttributes":0,"lightAbilities":0,"damageTypes":0},"trueStepIndex":0,"truePropertyIndex":0,"affectsLevel":false}],"exlusiveWithNodes":[3872169477,2947148901],"randomStartProgressionBarAtProgression":0},{"nodeIndex":10,"nodeHash":2947148901,"row":0,"column":4,"prerequisiteNodeIndexes":[],"binaryPairNodeIndex":-1,"autoUnlocks":false,"lastStepRepeats":false,"isRandom":false,"isRandomRepurchasable":false,"steps":[{"stepIndex":0,"nodeStepHash":4164836131,"nodeStepName":"Armor Piercing Rounds","nodeStepDescription":"These iridium-core rounds overpenetrate targets.\nTheir mass slows down weapon handling.","interactionDescription":"Upgrade","icon":"\/common\/destiny_content\/icons\/53310f5e62b6748ffd30a99e5d06e162.png","damageType":0,"activationRequirement":{"gridLevel":5,"materialRequirementHashes":[659267613]},"canActivateNextStep":false,"nextStepIndex":-1,"isNextStepRandom":false,"perkHashes":[3020342826],"startProgressionBarAtProgress":37500,"statHashes":[4043523819,943549884],"affectsQuality":false,"stepGroups":{"weaponPerformance":64,"impactEffects":0,"guardianAttributes":0,"lightAbilities":0,"damageTypes":0},"trueStepIndex":0,"truePropertyIndex":0,"affectsLevel":false}],"exlusiveWithNodes":[3872169477,3359939809],"randomStartProgressionBarAtProgression":0},{"nodeIndex":11,"nodeHash":312682976,"row":1,"column":1,"prerequisiteNodeIndexes":[],"binaryPairNodeIndex":-1,"autoUnlocks":false,"lastStepRepeats":false,"isRandom":false,"isRandomRepurchasable":false,"steps":[{"stepIndex":0,"nodeStepHash":2187318329,"nodeStepName":"Accurized Ballistics","nodeStepDescription":"More range and Impact. \nIncreased recoil.","interactionDescription":"Upgrade","icon":"\/common\/destiny_content\/icons\/8bffa8be796e8b0b27add34529a7d1d7.png","damageType":0,"activationRequirement":{"gridLevel":3,"materialRequirementHashes":[]},"canActivateNextStep":false,"nextStepIndex":-1,"isNextStepRandom":false,"perkHashes":[2868044506],"startProgressionBarAtProgress":7500,"statHashes":[1240592695,4043523819,155624089],"affectsQuality":false,"stepGroups":{"weaponPerformance":40,"impactEffects":0,"guardianAttributes":0,"lightAbilities":0,"damageTypes":0},"trueStepIndex":0,"truePropertyIndex":0,"affectsLevel":false}],"exlusiveWithNodes":[452419628,1503756812],"randomStartProgressionBarAtProgression":0},{"nodeIndex":12,"nodeHash":452419628,"row":0,"column":1,"prerequisiteNodeIndexes":[],"binaryPairNodeIndex":-1,"autoUnlocks":true,"lastStepRepeats":false,"isRandom":false,"isRandomRepurchasable":false,"steps":[{"stepIndex":0,"nodeStepHash":3532395338,"nodeStepName":"Soft Ballistics","nodeStepDescription":"Less recoil. \nPenalty to Impact.","interactionDescription":"Upgrade","icon":"\/common\/destiny_content\/icons\/4f26206cdc6fd31e0cdfe6b24ac2689c.png","damageType":0,"activationRequirement":{"gridLevel":0,"materialRequirementHashes":[]},"canActivateNextStep":false,"nextStepIndex":-1,"isNextStepRandom":false,"perkHashes":[2272440440],"startProgressionBarAtProgress":0,"statHashes":[4043523819,155624089],"affectsQuality":false,"stepGroups":{"weaponPerformance":32,"impactEffects":0,"guardianAttributes":0,"lightAbilities":0,"damageTypes":0},"trueStepIndex":0,"truePropertyIndex":0,"affectsLevel":false}],"exlusiveWithNodes":[312682976,1503756812],"randomStartProgressionBarAtProgression":0},{"nodeIndex":13,"nodeHash":1503756812,"row":2,"column":1,"prerequisiteNodeIndexes":[],"binaryPairNodeIndex":-1,"autoUnlocks":false,"lastStepRepeats":false,"isRandom":false,"isRandomRepurchasable":false,"steps":[{"stepIndex":0,"nodeStepHash":842241320,"nodeStepName":"Field Choke","nodeStepDescription":"More range and Impact. \nIncreased recoil.","interactionDescription":"Upgrade","icon":"\/common\/destiny_content\/icons\/2f6f4f9465d393f760f7e7d4fb9b3806.png","damageType":0,"activationRequirement":{"gridLevel":4,"materialRequirementHashes":[]},"canActivateNextStep":false,"nextStepIndex":-1,"isNextStepRandom":false,"perkHashes":[2868044506],"startProgressionBarAtProgress":22500,"statHashes":[1240592695,4043523819,155624089],"affectsQuality":false,"stepGroups":{"weaponPerformance":40,"impactEffects":0,"guardianAttributes":0,"lightAbilities":0,"damageTypes":0},"trueStepIndex":0,"truePropertyIndex":0,"affectsLevel":false}],"exlusiveWithNodes":[312682976,452419628],"randomStartProgressionBarAtProgression":0},{"nodeIndex":14,"nodeHash":99489719,"row":0,"column":6,"prerequisiteNodeIndexes":[],"binaryPairNodeIndex":-1,"autoUnlocks":false,"lastStepRepeats":false,"isRandom":false,"isRandomRepurchasable":false,"steps":[{"stepIndex":0,"nodeStepHash":491986635,"nodeStepName":"Upgrade Damage","nodeStepDescription":"Increases Attack Power, allowing this weapon to cause more damage.","interactionDescription":"Upgrade","icon":"\/common\/destiny_content\/icons\/2c564a7f220855661066d6a308940940.png","damageType":0,"activationRequirement":{"gridLevel":8,"materialRequirementHashes":[3021864743,3021864742,3021864741,3021864740]},"canActivateNextStep":false,"nextStepIndex":-1,"isNextStepRandom":false,"perkHashes":[],"startProgressionBarAtProgress":67500,"statHashes":[],"affectsQuality":true,"trueStepIndex":0,"truePropertyIndex":0,"affectsLevel":false}],"exlusiveWithNodes":[],"randomStartProgressionBarAtProgression":0},{"nodeIndex":15,"nodeHash":2658293415,"row":0,"column":-2,"prerequisiteNodeIndexes":[],"binaryPairNodeIndex":-1,"autoUnlocks":false,"lastStepRepeats":false,"isRandom":false,"isRandomRepurchasable":false,"steps":[{"stepIndex":0,"nodeStepHash":3809873841,"icon":"\/img\/misc\/missing_icon.png","damageType":0,"activationRequirement":{"gridLevel":0,"materialRequirementHashes":[]},"canActivateNextStep":false,"nextStepIndex":-1,"isNextStepRandom":false,"perkHashes":[646250337],"startProgressionBarAtProgress":0,"statHashes":[],"affectsQuality":false,"trueStepIndex":0,"truePropertyIndex":0,"affectsLevel":false}],"exlusiveWithNodes":[],"randomStartProgressionBarAtProgression":0}],"calcMaxGridLevel":0,"calcProgressToMaxLevel":0}},"statGroups":{"1232481893":{"statGroupHash":1232481893,"maximumValue":100,"uiPosition":0,"scaledStats":[{"statHash":4284893193,"maximumValue":100,"displayAsNumeric":false,"displayInterpolation":[{"value":0,"weight":59},{"value":9,"weight":59},{"value":10,"weight":66},{"value":39,"weight":66},{"value":40,"weight":77},{"value":79,"weight":77},{"value":80,"weight":88},{"value":99,"weight":88},{"value":100,"weight":100}]},{"statHash":4043523819,"maximumValue":100,"displayAsNumeric":false,"displayInterpolation":[{"value":0,"weight":25},{"value":100,"weight":65}]},{"statHash":1240592695,"maximumValue":100,"displayAsNumeric":false,"displayInterpolation":[{"value":0,"weight":2},{"value":100,"weight":52}]},{"statHash":155624089,"maximumValue":100,"displayAsNumeric":false,"displayInterpolation":[{"value":0,"weight":2},{"value":100,"weight":100}]},{"statHash":4188031367,"maximumValue":100,"displayAsNumeric":false,"displayInterpolation":[{"value":0,"weight":2},{"value":100,"weight":70}]},{"statHash":3871231066,"maximumValue":100,"displayAsNumeric":true,"displayInterpolation":[{"value":0,"weight":40},{"value":10,"weight":46},{"value":20,"weight":52},{"value":30,"weight":58},{"value":40,"weight":64},{"value":50,"weight":70},{"value":60,"weight":76},{"value":70,"weight":82},{"value":80,"weight":88},{"value":90,"weight":94},{"value":100,"weight":100}]}],"overrides":{}}},"progressionMappings":{},"sources":{},"progressions":{"1296042811":{"progressionHash":1296042811,"name":"weapon_superior_machinegun","scope":2,"repeatLastStep":true,"icon":"\/common\/destiny_content\/icons\/d898878d006bd02340a1f776738e50d9.png","steps":[{"progressTotal":0},{"progressTotal":7500},{"progressTotal":15000}]}},"materialRequirements":{},"factions":{},"events":{},"vendorSummaries":{},"activityBundles":{},"books":{}}}