{"data":{"requestedId":671526061,"inventoryItem":{"itemHash":671526061,"itemName":"\u00ab\u00a0Aspect du verre\u00a0\u00bb","itemDescription":"Vous filez, libre de toute contrainte, \u00e0 la poursuite de l'\u00e9ternit\u00e9.","icon":"\/common\/destiny_content\/icons\/0b04a1550c6e6778d62e0c9e5c89baa2.jpg","secondaryIcon":"\/img\/misc\/missing_icon.png","actionName":"Supprimer","tierTypeName":"L\u00e9gendaire","tierType":5,"itemTypeName":"Vaisseau","bucketTypeHash":284967655,"primaryBaseStatHash":0,"stats":{},"perkHashes":[],"specialItemType":0,"talentGridHash":521135891,"equippingBlock":{"weaponSandboxPatternIndex":21,"gearArtArrangementIndex":1195,"defaultDyes":[],"lockedDyes":[{"channelHash":284967655,"dyeHash":1437417001},{"channelHash":840921382,"dyeHash":2751843408}],"customDyes":[],"customDyeExpression":{"steps":[]},"weaponPatternHash":284967655},"hasGeometry":true,"statGroupHash":0,"itemLevels":[],"qualityLevel":0,"rewardItemHash":0,"values":{},"itemType":0,"itemSubType":0,"classType":3,"nonTransferrable":false,"exclusive":0,"maxStackSize":1},"talentGrid":{"gridHash":521135891,"maxGridLevel":0,"gridLevelPerColumn":0,"progressionHash":0,"nodes":[],"calcMaxGridLevel":0,"calcProgressToMaxLevel":0}},"definitions":{"destinations":{},"places":{},"activityTypes":{},"items":{},"buckets":{"284967655":{"bucketHash":284967655,"bucketName":"Vaisseaux","bucketDescription":"Ce vaisseau est \u00e0 votre disposition.","scope":0,"category":3,"bucketOrder":12,"bucketIdentifier":"BUCKET_SHIP","itemCount":10,"location":1,"hasTransferDestination":true}},"stats":{},"perks":{},"talentGrids":{"521135891":{"gridHash":521135891,"maxGridLevel":0,"gridLevelPerColumn":0,"progressionHash":0,"nodes":[],"calcMaxGridLevel":0,"calcProgressToMaxLevel":0}},"statGroups":{},"progressionMappings":{},"sources":{},"progressions":{},"materialRequirements":{},"factions":{},"events":{},"vendorSummaries":{},"activityBundles":{},"books":{}}}