{"data":{"requestedId":805224273,"inventoryItem":{"itemHash":805224273,"itemName":"\u30e9\u30c7\u30ac\u30b9\u30c8\u30ba\u30fb\u30d5\u30e5\u30fc\u30ea\u30fc","itemDescription":"\u30a2\u30a4\u30a2\u30f3\u30d0\u30ca\u30fc\u306e\u738b\u305f\u3061\u306e\u708e\u3067\u92f3\u9020\u3055\u308c\u305f\u30ed\u30b1\u30c3\u30c8\u30e9\u30f3\u30c1\u30e3\u30fc\u3002","icon":"\/common\/destiny_content\/icons\/5240b6f846c833991d35ff72ce9a8f14.jpg","secondaryIcon":"\/img\/misc\/missing_icon.png","actionName":"\u5206\u89e3","tierTypeName":"\u30ec\u30b8\u30a7\u30f3\u30c0\u30ea\u30fc","tierType":5,"itemTypeName":"\u30ed\u30b1\u30c3\u30c8\u30e9\u30f3\u30c1\u30e3\u30fc","bucketTypeHash":953998645,"primaryBaseStatHash":368428387,"stats":{"368428387":{"statHash":368428387,"value":272,"minimum":272,"maximum":331},"3555269338":{"statHash":3555269338,"value":20,"minimum":20,"maximum":20},"4284893193":{"statHash":4284893193,"value":4,"minimum":4,"maximum":4},"3614673599":{"statHash":3614673599,"value":96,"minimum":94,"maximum":100},"2523465841":{"statHash":2523465841,"value":64,"minimum":61,"maximum":90},"155624089":{"statHash":155624089,"value":22,"minimum":22,"maximum":81},"3871231066":{"statHash":3871231066,"value":1,"minimum":1,"maximum":2},"4188031367":{"statHash":4188031367,"value":62,"minimum":62,"maximum":100},"1931675084":{"statHash":1931675084,"value":60,"minimum":60,"maximum":140},"943549884":{"statHash":943549884,"value":35,"minimum":35,"maximum":35},"1345609583":{"statHash":1345609583,"value":23,"minimum":23,"maximum":23},"2715839340":{"statHash":2715839340,"value":79,"minimum":79,"maximum":99}},"perkHashes":[3453522274,805224273],"specialItemType":0,"talentGridHash":3821688456,"equippingBlock":{"weaponSandboxPatternIndex":18,"gearArtArrangementIndex":1300,"defaultDyes":[],"lockedDyes":[{"channelHash":1667433279,"dyeHash":344135154},{"channelHash":1667433278,"dyeHash":13752169}],"customDyes":[],"customDyeExpression":{"steps":[]},"weaponPatternHash":660767731},"hasGeometry":true,"statGroupHash":660767731,"itemLevels":[0],"qualityLevel":60,"rewardItemHash":0,"values":{},"itemType":3,"itemSubType":10,"classType":3,"nonTransferrable":false,"exclusive":0,"maxStackSize":1},"talentGrid":{"gridHash":3821688456,"maxGridLevel":0,"gridLevelPerColumn":0,"progressionHash":1054627247,"nodes":[{"nodeIndex":0,"nodeHash":402641165,"row":0,"column":0,"prerequisiteNodeIndexes":[],"binaryPairNodeIndex":-1,"autoUnlocks":true,"lastStepRepeats":false,"isRandom":true,"randomActivationRequirement":{"gridLevel":0},"isRandomRepurchasable":false,"steps":[{"stepIndex":0,"nodeStepHash":4134271514,"nodeStepName":"\u30dc\u30a4\u30c9\u30fb\u30c0\u30e1\u30fc\u30b8","nodeStepDescription":"\u30dc\u30a4\u30c9\u30fb\u30c0\u30e1\u30fc\u30b8\u3092\u4e0e\u3048\u308b\u3002","interactionDescription":"\u30ea\u30ed\u30fc\u30eb","icon":"\/common\/destiny_content\/icons\/bc527dbbeed646129dbda1a29f719fc3.png","damageType":4,"activationRequirement":{"gridLevel":0,"materialRequirementHashes":[]},"canActivateNextStep":false,"nextStepIndex":-1,"isNextStepRandom":true,"perkHashes":[3614988247],"startProgressionBarAtProgress":0,"statHashes":[],"affectsQuality":false,"stepGroups":{"weaponPerformance":0,"impactEffects":0,"guardianAttributes":0,"lightAbilities":0,"damageTypes":8},"trueStepIndex":0,"truePropertyIndex":0,"affectsLevel":false},{"stepIndex":1,"nodeStepHash":2093640965,"nodeStepName":"\u30bd\u30fc\u30e9\u30fc\u30c0\u30e1\u30fc\u30b8","nodeStepDescription":"\u30bd\u30fc\u30e9\u30fc\u30c0\u30e1\u30fc\u30b8\u3092\u4e0e\u3048\u308b\u3002","interactionDescription":"\u30ea\u30ed\u30fc\u30eb","icon":"\/common\/destiny_content\/icons\/c2fad8059225eed26742c4b293f424ec.png","damageType":3,"activationRequirement":{"gridLevel":0,"materialRequirementHashes":[]},"canActivateNextStep":false,"nextStepIndex":-1,"isNextStepRandom":true,"perkHashes":[233596484],"startProgressionBarAtProgress":0,"statHashes":[],"affectsQuality":false,"stepGroups":{"weaponPerformance":0,"impactEffects":0,"guardianAttributes":0,"lightAbilities":0,"damageTypes":4},"trueStepIndex":0,"truePropertyIndex":0,"affectsLevel":false},{"stepIndex":2,"nodeStepHash":1859696124,"nodeStepName":"\u30a2\u30fc\u30af\u30fb\u30c0\u30e1\u30fc\u30b8","nodeStepDescription":"\u30a2\u30fc\u30af\u30fb\u30c0\u30e1\u30fc\u30b8\u3092\u4e0e\u3048\u308b\u3002","interactionDescription":"\u30ea\u30ed\u30fc\u30eb","icon":"\/common\/destiny_content\/icons\/2a7123978a4da00f33e456fef6e9065a.png","damageType":2,"activationRequirement":{"gridLevel":0,"materialRequirementHashes":[]},"canActivateNextStep":false,"nextStepIndex":-1,"isNextStepRandom":true,"perkHashes":[839929915],"startProgressionBarAtProgress":0,"statHashes":[],"affectsQuality":false,"stepGroups":{"weaponPerformance":0,"impactEffects":0,"guardianAttributes":0,"lightAbilities":0,"damageTypes":2},"trueStepIndex":0,"truePropertyIndex":0,"affectsLevel":false}],"exlusiveWithNodes":[],"randomStartProgressionBarAtProgression":0},{"nodeIndex":1,"nodeHash":312682976,"row":1,"column":1,"prerequisiteNodeIndexes":[],"binaryPairNodeIndex":-1,"autoUnlocks":false,"lastStepRepeats":false,"isRandom":true,"randomActivationRequirement":{"gridLevel":0},"isRandomRepurchasable":false,"steps":[{"stepIndex":0,"nodeStepHash":4219019438,"nodeStepName":"\u30bd\u30d5\u30c8\u30b7\u30e7\u30c3\u30c8","nodeStepDescription":"\u53cd\u52d5\u3092\u8efd\u6e1b\u3059\u308b\u3002\n\u305f\u3060\u3057\u901f\u5ea6\u304c\u843d\u3061\u308b\u3002","interactionDescription":"\u30a2\u30c3\u30d7\u30b0\u30ec\u30fc\u30c9","icon":"\/common\/destiny_content\/icons\/5f850325aadf7b61a78342fc9d30687c.png","damageType":0,"activationRequirement":{"gridLevel":3,"materialRequirementHashes":[2949229212]},"canActivateNextStep":false,"nextStepIndex":-1,"isNextStepRandom":true,"perkHashes":[],"startProgressionBarAtProgress":7500,"statHashes":[2523465841,155624089],"affectsQuality":false,"stepGroups":{"weaponPerformance":32,"impactEffects":0,"guardianAttributes":0,"lightAbilities":0,"damageTypes":0},"trueStepIndex":0,"truePropertyIndex":0,"affectsLevel":false},{"stepIndex":1,"nodeStepHash":183788411,"nodeStepName":"\u30ea\u30cb\u30a2\u30fb\u30b3\u30f3\u30da\u30f3\u30bb\u30a4\u30bf\u30fc","nodeStepDescription":"\u53cd\u52d5\u304c\u898f\u5247\u7684\u306b\u306a\u308b\u3002\n\u901f\u5ea6\u3068\u7206\u767a\u7bc4\u56f2\u3092\u308f\u305a\u304b\u306b\u5f37\u5316\u3059\u308b\u3002\n\u53cd\u52d5\u306f\u5927\u304d\u304f\u306a\u308b\u3002","interactionDescription":"\u30a2\u30c3\u30d7\u30b0\u30ec\u30fc\u30c9","icon":"\/common\/destiny_content\/icons\/5f850325aadf7b61a78342fc9d30687c.png","damageType":0,"activationRequirement":{"gridLevel":3,"materialRequirementHashes":[2949229212]},"canActivateNextStep":false,"nextStepIndex":-1,"isNextStepRandom":true,"perkHashes":[2868044506],"startProgressionBarAtProgress":7500,"statHashes":[2523465841,3614673599,2715839340,155624089],"affectsQuality":false,"stepGroups":{"weaponPerformance":1056,"impactEffects":0,"guardianAttributes":0,"lightAbilities":0,"damageTypes":0},"trueStepIndex":0,"truePropertyIndex":0,"affectsLevel":false},{"stepIndex":2,"nodeStepHash":443524680,"nodeStepName":"\u30b9\u30de\u30fc\u30c8\u30fb\u30c9\u30ea\u30d5\u30c8\u30fb\u30b3\u30f3\u30c8\u30ed\u30fc\u30eb","nodeStepDescription":"\u898f\u5247\u7684\u306a\u53cd\u52d5\u3067\u5236\u5fa1\u3057\u3084\u3059\u304f\u306a\u308b\u3002\n\u901f\u5ea6\u304c\u843d\u3061\u308b\u3002","interactionDescription":"\u30a2\u30c3\u30d7\u30b0\u30ec\u30fc\u30c9","icon":"\/common\/destiny_content\/icons\/5f850325aadf7b61a78342fc9d30687c.png","damageType":0,"activationRequirement":{"gridLevel":3,"materialRequirementHashes":[2949229212]},"canActivateNextStep":false,"nextStepIndex":-1,"isNextStepRandom":true,"perkHashes":[],"startProgressionBarAtProgress":7500,"statHashes":[2523465841,2715839340,155624089],"affectsQuality":false,"stepGroups":{"weaponPerformance":32,"impactEffects":0,"guardianAttributes":0,"lightAbilities":0,"damageTypes":0},"trueStepIndex":0,"truePropertyIndex":0,"affectsLevel":false}],"exlusiveWithNodes":[452419628,1503756812],"randomStartProgressionBarAtProgression":0},{"nodeIndex":2,"nodeHash":3872169477,"row":2,"column":4,"prerequisiteNodeIndexes":[],"binaryPairNodeIndex":-1,"autoUnlocks":false,"lastStepRepeats":false,"isRandom":true,"randomActivationRequirement":{"gridLevel":0},"isRandomRepurchasable":false,"steps":[{"stepIndex":0,"nodeStepHash":3969014851,"nodeStepName":"\u30b9\u30ca\u30c3\u30d7\u30b7\u30e7\u30c3\u30c8","nodeStepDescription":"\u72d9\u3046\u901f\u3055\u304c\u6975\u7aef\u306b\u4e0a\u304c\u308b\u3002","interactionDescription":"\u30a2\u30c3\u30d7\u30b0\u30ec\u30fc\u30c9","icon":"\/common\/destiny_content\/icons\/ed61618f32ec01329a59ab37ea9934ce.png","damageType":0,"activationRequirement":{"gridLevel":7,"materialRequirementHashes":[391095254]},"canActivateNextStep":false,"nextStepIndex":-1,"isNextStepRandom":true,"perkHashes":[1563623317],"startProgressionBarAtProgress":67500,"statHashes":[],"affectsQuality":false,"stepGroups":{"weaponPerformance":64,"impactEffects":0,"guardianAttributes":0,"lightAbilities":0,"damageTypes":0},"trueStepIndex":0,"truePropertyIndex":0,"affectsLevel":false},{"stepIndex":1,"nodeStepHash":2104465304,"nodeStepName":"\u30b8\u30e3\u30d9\u30ea\u30f3","nodeStepDescription":"\u5f3e\u306e\u901f\u5ea6\u304c\u4e0a\u6607\u3059\u308b\u3002","interactionDescription":"\u30a2\u30c3\u30d7\u30b0\u30ec\u30fc\u30c9","icon":"\/common\/destiny_content\/icons\/5f850325aadf7b61a78342fc9d30687c.png","damageType":0,"activationRequirement":{"gridLevel":7,"materialRequirementHashes":[391095254]},"canActivateNextStep":false,"nextStepIndex":-1,"isNextStepRandom":true,"perkHashes":[],"startProgressionBarAtProgress":67500,"statHashes":[2523465841],"affectsQuality":false,"stepGroups":{"weaponPerformance":0,"impactEffects":0,"guardianAttributes":0,"lightAbilities":0,"damageTypes":0},"trueStepIndex":0,"truePropertyIndex":0,"affectsLevel":false},{"stepIndex":2,"nodeStepHash":3241612944,"nodeStepName":"\u30d5\u30a3\u30fc\u30eb\u30c9\u30b9\u30ab\u30a6\u30c8","nodeStepDescription":"\u5f3e\u4e38\u6700\u5927\u6570\u3002","interactionDescription":"\u30a2\u30c3\u30d7\u30b0\u30ec\u30fc\u30c9","icon":"\/common\/destiny_content\/icons\/0aeba7e8935ea9f58dd314faf4fc6018.png","damageType":0,"activationRequirement":{"gridLevel":7,"materialRequirementHashes":[391095254]},"canActivateNextStep":false,"nextStepIndex":-1,"isNextStepRandom":true,"perkHashes":[],"startProgressionBarAtProgress":67500,"statHashes":[3871231066,1931675084],"affectsQuality":false,"stepGroups":{"weaponPerformance":512,"impactEffects":0,"guardianAttributes":0,"lightAbilities":0,"damageTypes":0},"trueStepIndex":0,"truePropertyIndex":0,"affectsLevel":false}],"exlusiveWithNodes":[3359939809,2947148901],"randomStartProgressionBarAtProgression":0},{"nodeIndex":3,"nodeHash":3678843182,"row":0,"column":3,"prerequisiteNodeIndexes":[],"binaryPairNodeIndex":-1,"autoUnlocks":false,"lastStepRepeats":false,"isRandom":false,"isRandomRepurchasable":false,"steps":[{"stepIndex":0,"nodeStepHash":491986635,"nodeStepName":"\u30c0\u30e1\u30fc\u30b8\u5f37\u5316","nodeStepDescription":"\u3053\u306e\u6b66\u5668\u306e\u653b\u6483\u529b\u3092\u4e0a\u6607\u3055\u305b\u3066\u4e0e\u3048\u308b\u30c0\u30e1\u30fc\u30b8\u3092\u5897\u52a0\u3055\u305b\u308b\u3002","interactionDescription":"\u30a2\u30c3\u30d7\u30b0\u30ec\u30fc\u30c9","icon":"\/common\/destiny_content\/icons\/2c564a7f220855661066d6a308940940.png","damageType":0,"activationRequirement":{"gridLevel":4,"materialRequirementHashes":[3105527295,3105527294,3105527293,3105527292]},"canActivateNextStep":false,"nextStepIndex":-1,"isNextStepRandom":false,"perkHashes":[],"startProgressionBarAtProgress":7500,"statHashes":[],"affectsQuality":true,"trueStepIndex":0,"truePropertyIndex":0,"affectsLevel":false}],"exlusiveWithNodes":[],"randomStartProgressionBarAtProgression":0},{"nodeIndex":4,"nodeHash":4076480290,"row":0,"column":5,"prerequisiteNodeIndexes":[],"binaryPairNodeIndex":-1,"autoUnlocks":false,"lastStepRepeats":false,"isRandom":true,"randomActivationRequirement":{"gridLevel":0},"isRandomRepurchasable":false,"steps":[{"stepIndex":0,"nodeStepHash":3953138191,"nodeStepName":"\u30af\u30e9\u30a6\u30f3\u30fb\u30ab\u30fc\u30c8\u30ea\u30c3\u30b8","nodeStepDescription":"\u30ea\u30ed\u30fc\u30c9\u3059\u308b\u3068\u3001\u4e00\u5b9a\u306e\u78ba\u7387\u3067\u901a\u5e38\u3088\u308a\u5927\u304d\u306a\u30de\u30ac\u30b8\u30f3\u3092\u7372\u5f97\u3067\u304d\u308b\u3002","interactionDescription":"\u30a2\u30c3\u30d7\u30b0\u30ec\u30fc\u30c9","icon":"\/common\/destiny_content\/icons\/1029fc6f5ba1086258c42e1e31577be9.png","damageType":0,"activationRequirement":{"gridLevel":6,"materialRequirementHashes":[391095254]},"canActivateNextStep":false,"nextStepIndex":-1,"isNextStepRandom":true,"perkHashes":[3052118152],"startProgressionBarAtProgress":52500,"statHashes":[],"affectsQuality":false,"stepGroups":{"weaponPerformance":512,"impactEffects":0,"guardianAttributes":0,"lightAbilities":0,"damageTypes":0},"trueStepIndex":0,"truePropertyIndex":0,"affectsLevel":false},{"stepIndex":1,"nodeStepHash":4019183967,"nodeStepName":"\u30b0\u30ec\u30cd\u30fc\u30c0\u30fc","nodeStepDescription":"\u6575\u3092\u5012\u3059\u3068\u3001\u30b0\u30ec\u30cd\u30fc\u30c9\u306e\u30af\u30fc\u30eb\u30c0\u30a6\u30f3\u6642\u9593\u304c\u77ed\u7e2e\u3055\u308c\u308b\u3002","interactionDescription":"\u30a2\u30c3\u30d7\u30b0\u30ec\u30fc\u30c9","icon":"\/common\/destiny_content\/icons\/ea01cd5a7c3962ad1798ec56bb6f25dc.png","damageType":0,"activationRequirement":{"gridLevel":6,"materialRequirementHashes":[391095254]},"canActivateNextStep":false,"nextStepIndex":-1,"isNextStepRandom":true,"perkHashes":[3283108368],"startProgressionBarAtProgress":52500,"statHashes":[],"affectsQuality":false,"stepGroups":{"weaponPerformance":0,"impactEffects":0,"guardianAttributes":0,"lightAbilities":1,"damageTypes":0},"trueStepIndex":0,"truePropertyIndex":0,"affectsLevel":false},{"stepIndex":2,"nodeStepHash":1474605717,"nodeStepName":"\u5438\u5f15","nodeStepDescription":"\u3053\u306e\u6b66\u5668\u306e\u843d\u3061\u3066\u3044\u308b\u5f3e\u4e38\u306e\u56de\u53ce\u7bc4\u56f2\u304c\u5e83\u304f\u306a\u308b\u3002","interactionDescription":"\u30a2\u30c3\u30d7\u30b0\u30ec\u30fc\u30c9","icon":"\/common\/destiny_content\/icons\/412dc6211f5349af8dff0c6318c52871.png","damageType":0,"activationRequirement":{"gridLevel":6,"materialRequirementHashes":[391095254]},"canActivateNextStep":false,"nextStepIndex":-1,"isNextStepRandom":true,"perkHashes":[1989386514],"startProgressionBarAtProgress":52500,"statHashes":[],"affectsQuality":false,"stepGroups":{"weaponPerformance":512,"impactEffects":0,"guardianAttributes":0,"lightAbilities":0,"damageTypes":0},"trueStepIndex":0,"truePropertyIndex":0,"affectsLevel":false},{"stepIndex":3,"nodeStepHash":2419743018,"nodeStepName":"\u30b9\u30d4\u30fc\u30c9\u30d7\u30ec\u30a4","nodeStepDescription":"\u3053\u306e\u6b66\u5668\u306e\u9283\u5009\u304c\u7a7a\u306b\u306a\u3063\u305f\u6642\u306e\u30ea\u30ed\u30fc\u30c9\u901f\u5ea6\u304c\u4e0a\u304c\u308b\u3002","interactionDescription":"\u30a2\u30c3\u30d7\u30b0\u30ec\u30fc\u30c9","icon":"\/common\/destiny_content\/icons\/65a3714fdd2cb2506df6bd6d04f3ca41.png","damageType":0,"activationRequirement":{"gridLevel":6,"materialRequirementHashes":[391095254]},"canActivateNextStep":false,"nextStepIndex":-1,"isNextStepRandom":true,"perkHashes":[192233393],"startProgressionBarAtProgress":52500,"statHashes":[],"affectsQuality":false,"stepGroups":{"weaponPerformance":128,"impactEffects":0,"guardianAttributes":0,"lightAbilities":0,"damageTypes":0},"trueStepIndex":0,"truePropertyIndex":0,"affectsLevel":false},{"stepIndex":4,"nodeStepHash":3321026111,"nodeStepName":"\u7b2c\u4e09\u306e\u76ee","nodeStepDescription":"\u3053\u306e\u7167\u6e96\u5668\u3067\u72d9\u3044\u3092\u5b9a\u3081\u3066\u3044\u308b\u9593\u3001\u30ec\u30fc\u30c0\u30fc\u304c\u6709\u52b9\u306b\u306a\u308b\u3002","interactionDescription":"\u30a2\u30c3\u30d7\u30b0\u30ec\u30fc\u30c9","icon":"\/common\/destiny_content\/icons\/cebc6a446ed2bbd135042afcde658050.png","damageType":0,"activationRequirement":{"gridLevel":6,"materialRequirementHashes":[391095254]},"canActivateNextStep":false,"nextStepIndex":-1,"isNextStepRandom":true,"perkHashes":[770631416],"startProgressionBarAtProgress":52500,"statHashes":[],"affectsQuality":false,"stepGroups":{"weaponPerformance":0,"impactEffects":0,"guardianAttributes":32,"lightAbilities":0,"damageTypes":0},"trueStepIndex":0,"truePropertyIndex":0,"affectsLevel":false},{"stepIndex":5,"nodeStepHash":3499432131,"nodeStepName":"\u30d5\u30fc\u30ba\u30fb\u30cd\u30af\u30b9\u30c8","nodeStepDescription":"\u30de\u30ac\u30b8\u30f3\u306e\u6700\u5f8c\u306e\u4e00\u767a\u3067\u6575\u3092\u5012\u3059\u3068\u3001\u30ea\u30ed\u30fc\u30c9\u901f\u5ea6\u304c\u4e0a\u6607\u3059\u308b\u3002","interactionDescription":"\u30a2\u30c3\u30d7\u30b0\u30ec\u30fc\u30c9","icon":"\/common\/destiny_content\/icons\/2f704829126a379841a362dd5e3ec11a.png","damageType":0,"activationRequirement":{"gridLevel":6,"materialRequirementHashes":[391095254]},"canActivateNextStep":false,"nextStepIndex":-1,"isNextStepRandom":true,"perkHashes":[3686406336],"startProgressionBarAtProgress":52500,"statHashes":[],"affectsQuality":false,"stepGroups":{"weaponPerformance":128,"impactEffects":0,"guardianAttributes":0,"lightAbilities":0,"damageTypes":0},"trueStepIndex":0,"truePropertyIndex":0,"affectsLevel":false}],"exlusiveWithNodes":[],"randomStartProgressionBarAtProgression":0},{"nodeIndex":5,"nodeHash":3452924987,"row":0,"column":2,"prerequisiteNodeIndexes":[],"binaryPairNodeIndex":-1,"autoUnlocks":false,"lastStepRepeats":false,"isRandom":true,"randomActivationRequirement":{"gridLevel":0},"isRandomRepurchasable":false,"steps":[{"stepIndex":0,"nodeStepHash":1586312458,"nodeStepName":"\u30af\u30e9\u30b9\u30bf\u30fc\u7206\u5f3e","nodeStepDescription":"\u30ed\u30b1\u30c3\u30c8\u304c\u7206\u767a\u3059\u308b\u6642\u306b\u30af\u30e9\u30b9\u30bf\u30fc\u7206\u5f3e\u304c\u751f\u6210\u3055\u308c\u308b\u3002","interactionDescription":"\u30ea\u30ed\u30fc\u30eb","icon":"\/common\/destiny_content\/icons\/9291c3a5e1f9f5f9a93ab1c60b4f292b.png","damageType":0,"activationRequirement":{"gridLevel":2,"materialRequirementHashes":[391095254]},"canActivateNextStep":false,"nextStepIndex":-1,"isNextStepRandom":true,"perkHashes":[1928591453],"startProgressionBarAtProgress":0,"statHashes":[],"affectsQuality":false,"stepGroups":{"weaponPerformance":1026,"impactEffects":8,"guardianAttributes":0,"lightAbilities":0,"damageTypes":0},"trueStepIndex":0,"truePropertyIndex":0,"affectsLevel":false},{"stepIndex":1,"nodeStepHash":889898201,"nodeStepName":"\u30b0\u30ec\u30cd\u30fc\u30c9&\u30db\u30fc\u30b9\u30b7\u30e5\u30fc\u30ba","nodeStepDescription":"\u767a\u5c04\u3057\u305f\u30ed\u30b1\u30c3\u30c8\u304c\u6a19\u7684\u3068\u306e\u8ddd\u96e2\u306b\u5fdc\u3058\u3066\u65e9\u3081\u306b\u7206\u767a\u3059\u308b\u3002","interactionDescription":"\u30a2\u30c3\u30d7\u30b0\u30ec\u30fc\u30c9","icon":"\/common\/destiny_content\/icons\/11d8f24e309d29aa4d7bc707d35d2b2b.png","damageType":0,"activationRequirement":{"gridLevel":2,"materialRequirementHashes":[391095254]},"canActivateNextStep":false,"nextStepIndex":-1,"isNextStepRandom":true,"perkHashes":[2425591494],"startProgressionBarAtProgress":0,"statHashes":[],"affectsQuality":false,"stepGroups":{"weaponPerformance":1024,"impactEffects":0,"guardianAttributes":0,"lightAbilities":0,"damageTypes":0},"trueStepIndex":0,"truePropertyIndex":0,"affectsLevel":false},{"stepIndex":2,"nodeStepHash":2828711099,"nodeStepName":"\u5c48\u5f37","nodeStepDescription":"\u3053\u306e\u6b66\u5668\u3092\u4f7f\u7528\u3059\u308b\u3068\u3001\u653b\u6483\u3092\u53d7\u3051\u3066\u308b\u9593\u3082\u72d9\u3044\u3092\u3064\u3051\u3084\u3059\u304f\u306a\u308b\u3002","interactionDescription":"\u30a2\u30c3\u30d7\u30b0\u30ec\u30fc\u30c9","icon":"\/common\/destiny_content\/icons\/56b0a618702427e1257282487b7702b7.png","damageType":0,"activationRequirement":{"gridLevel":2,"materialRequirementHashes":[391095254]},"canActivateNextStep":false,"nextStepIndex":-1,"isNextStepRandom":true,"perkHashes":[2626112550],"startProgressionBarAtProgress":0,"statHashes":[],"affectsQuality":false,"stepGroups":{"weaponPerformance":0,"impactEffects":0,"guardianAttributes":16,"lightAbilities":0,"damageTypes":0},"trueStepIndex":0,"truePropertyIndex":0,"affectsLevel":false},{"stepIndex":3,"nodeStepHash":982758423,"nodeStepName":"\u30de\u30ea\u30ac\u30f3","nodeStepDescription":"\u547d\u4e2d\u3057\u306a\u304b\u3063\u305f\u5f3e\u304c\u4e00\u5b9a\u306e\u78ba\u7387\u3067\u76f4\u63a5\u30de\u30ac\u30b8\u30f3\u306b\u623b\u308b\u3002","interactionDescription":"\u30a2\u30c3\u30d7\u30b0\u30ec\u30fc\u30c9","icon":"\/common\/destiny_content\/icons\/6c5d493501c71c960b9313ef30eccf23.png","damageType":0,"activationRequirement":{"gridLevel":2,"materialRequirementHashes":[391095254]},"canActivateNextStep":false,"nextStepIndex":-1,"isNextStepRandom":true,"perkHashes":[824061322],"startProgressionBarAtProgress":0,"statHashes":[],"affectsQuality":false,"stepGroups":{"weaponPerformance":512,"impactEffects":0,"guardianAttributes":0,"lightAbilities":0,"damageTypes":0},"trueStepIndex":0,"truePropertyIndex":0,"affectsLevel":false},{"stepIndex":4,"nodeStepHash":3110691286,"nodeStepName":"\u30b5\u30fc\u30d7\u30e9\u30b9","nodeStepDescription":"\u843d\u3061\u3066\u3044\u308b\u5f3e\u85ac\u3092\u767a\u898b\u3057\u3084\u3059\u304f\u306a\u308b\u3002","interactionDescription":"\u30a2\u30c3\u30d7\u30b0\u30ec\u30fc\u30c9","icon":"\/common\/destiny_content\/icons\/d15829c40438313bb8c3226d3763e097.png","damageType":0,"activationRequirement":{"gridLevel":2,"materialRequirementHashes":[391095254]},"canActivateNextStep":false,"nextStepIndex":-1,"isNextStepRandom":true,"perkHashes":[3317503477],"startProgressionBarAtProgress":0,"statHashes":[],"affectsQuality":false,"stepGroups":{"weaponPerformance":512,"impactEffects":0,"guardianAttributes":0,"lightAbilities":0,"damageTypes":0},"trueStepIndex":0,"truePropertyIndex":0,"affectsLevel":false},{"stepIndex":5,"nodeStepHash":4178265121,"nodeStepName":"\u30c8\u30e9\u30a4\u30dd\u30c3\u30c9","nodeStepDescription":"\u3053\u306e\u30e9\u30f3\u30c1\u30e3\u30fc\u306f3\u767a\u307e\u3067\u5f3e\u3092\u88c5\u586b\u3067\u304d\u308b\u3002","interactionDescription":"\u30a2\u30c3\u30d7\u30b0\u30ec\u30fc\u30c9","icon":"\/common\/destiny_content\/icons\/df172f27e76198675ab8d8ace1ef5b19.png","damageType":0,"activationRequirement":{"gridLevel":2,"materialRequirementHashes":[391095254]},"canActivateNextStep":false,"nextStepIndex":-1,"isNextStepRandom":true,"perkHashes":[2784842908],"startProgressionBarAtProgress":0,"statHashes":[],"affectsQuality":false,"stepGroups":{"weaponPerformance":512,"impactEffects":0,"guardianAttributes":0,"lightAbilities":0,"damageTypes":0},"trueStepIndex":0,"truePropertyIndex":0,"affectsLevel":false},{"stepIndex":6,"nodeStepHash":2976905221,"nodeStepName":"\u30c8\u30e9\u30c3\u30ad\u30f3\u30b0","nodeStepDescription":"\u30db\u30fc\u30df\u30f3\u30b0\u5f3e\u3092\u6483\u3066\u308b\u3002","interactionDescription":"\u30a2\u30c3\u30d7\u30b0\u30ec\u30fc\u30c9","icon":"\/common\/destiny_content\/icons\/7fb28865684ccbca32bb642b0c66821b.png","damageType":0,"activationRequirement":{"gridLevel":2,"materialRequirementHashes":[391095254]},"canActivateNextStep":false,"nextStepIndex":-1,"isNextStepRandom":true,"perkHashes":[2179933840],"startProgressionBarAtProgress":0,"statHashes":[],"affectsQuality":false,"stepGroups":{"weaponPerformance":1024,"impactEffects":0,"guardianAttributes":0,"lightAbilities":0,"damageTypes":0},"trueStepIndex":0,"truePropertyIndex":0,"affectsLevel":false}],"exlusiveWithNodes":[],"randomStartProgressionBarAtProgression":0},{"nodeIndex":6,"nodeHash":452419628,"row":0,"column":1,"prerequisiteNodeIndexes":[],"binaryPairNodeIndex":-1,"autoUnlocks":true,"lastStepRepeats":false,"isRandom":true,"randomActivationRequirement":{"gridLevel":0},"isRandomRepurchasable":false,"steps":[{"stepIndex":0,"nodeStepHash":2873942429,"nodeStepName":"\u30a6\u30a9\u30fc\u30d8\u30c3\u30c9\u30fb\u30d9\u30cb\u30fc\u30eb","nodeStepDescription":"\u901f\u5ea6\u3068\u7206\u767a\u7bc4\u56f2\u3092\u5f37\u5316\u3059\u308b\u3002\n\u53cd\u52d5\u304c\u5927\u304d\u304f\u306a\u308b\u3002","interactionDescription":"\u30a2\u30c3\u30d7\u30b0\u30ec\u30fc\u30c9","icon":"\/common\/destiny_content\/icons\/5f850325aadf7b61a78342fc9d30687c.png","damageType":0,"activationRequirement":{"gridLevel":0,"materialRequirementHashes":[]},"canActivateNextStep":false,"nextStepIndex":-1,"isNextStepRandom":true,"perkHashes":[2868044506],"startProgressionBarAtProgress":0,"statHashes":[2523465841,3614673599,155624089],"affectsQuality":false,"stepGroups":{"weaponPerformance":1056,"impactEffects":0,"guardianAttributes":0,"lightAbilities":0,"damageTypes":0},"trueStepIndex":0,"truePropertyIndex":0,"affectsLevel":false},{"stepIndex":1,"nodeStepHash":3133678698,"nodeStepName":"\u30b3\u30f3\u30d5\u30a1\u30a4\u30f3\u30c9\u30fb\u30ed\u30fc\u30f3\u30c1","nodeStepDescription":"\u53cd\u52d5\u3092\u5927\u5e45\u306b\u8efd\u6e1b\u3059\u308b\u3002\n\u901f\u5ea6\u304c\u5927\u5e45\u306b\u843d\u3061\u308b\u3002","interactionDescription":"\u30a2\u30c3\u30d7\u30b0\u30ec\u30fc\u30c9","icon":"\/common\/destiny_content\/icons\/5f850325aadf7b61a78342fc9d30687c.png","damageType":0,"activationRequirement":{"gridLevel":0,"materialRequirementHashes":[]},"canActivateNextStep":false,"nextStepIndex":-1,"isNextStepRandom":true,"perkHashes":[],"startProgressionBarAtProgress":0,"statHashes":[2523465841,155624089],"affectsQuality":false,"stepGroups":{"weaponPerformance":32,"impactEffects":0,"guardianAttributes":0,"lightAbilities":0,"damageTypes":0},"trueStepIndex":0,"truePropertyIndex":0,"affectsLevel":false},{"stepIndex":2,"nodeStepHash":1788601689,"nodeStepName":"\u30a2\u30b0\u30ec\u30c3\u30b7\u30d6\u30b7\u30e7\u30c3\u30c8","nodeStepDescription":"\u53cd\u52d5\u304c\u898f\u5247\u7684\u306b\u306a\u308b\u3002\n\u7206\u767a\u7bc4\u56f2\u304c\u5897\u5927\u3059\u308b\u3002\n\u901f\u5ea6\u304c\u843d\u3061\u3001\u53cd\u52d5\u304c\u5927\u304d\u304f\u306a\u308b\u3002","interactionDescription":"\u30a2\u30c3\u30d7\u30b0\u30ec\u30fc\u30c9","icon":"\/common\/destiny_content\/icons\/5f850325aadf7b61a78342fc9d30687c.png","damageType":0,"activationRequirement":{"gridLevel":0,"materialRequirementHashes":[]},"canActivateNextStep":false,"nextStepIndex":-1,"isNextStepRandom":true,"perkHashes":[3097446979],"startProgressionBarAtProgress":0,"statHashes":[2523465841,3614673599,2715839340,155624089],"affectsQuality":false,"stepGroups":{"weaponPerformance":1056,"impactEffects":0,"guardianAttributes":0,"lightAbilities":0,"damageTypes":0},"trueStepIndex":0,"truePropertyIndex":0,"affectsLevel":false}],"exlusiveWithNodes":[312682976,1503756812],"randomStartProgressionBarAtProgression":0},{"nodeIndex":7,"nodeHash":1503756812,"row":2,"column":1,"prerequisiteNodeIndexes":[],"binaryPairNodeIndex":-1,"autoUnlocks":false,"lastStepRepeats":false,"isRandom":true,"randomActivationRequirement":{"gridLevel":0},"isRandomRepurchasable":false,"steps":[{"stepIndex":0,"nodeStepHash":1269129151,"nodeStepName":"\u30ab\u30a6\u30f3\u30bf\u30fc\u30de\u30b9","nodeStepDescription":"\u53cd\u52d5\u3092\u8efd\u6e1b\u3002\n\u7206\u767a\u7bc4\u56f2\u304c\u72ed\u307e\u308b\u3002","interactionDescription":"\u30a2\u30c3\u30d7\u30b0\u30ec\u30fc\u30c9","icon":"\/common\/destiny_content\/icons\/5f850325aadf7b61a78342fc9d30687c.png","damageType":0,"activationRequirement":{"gridLevel":4,"materialRequirementHashes":[2949229212]},"canActivateNextStep":false,"nextStepIndex":-1,"isNextStepRandom":true,"perkHashes":[2272440440],"startProgressionBarAtProgress":22500,"statHashes":[3614673599,155624089],"affectsQuality":false,"stepGroups":{"weaponPerformance":1056,"impactEffects":0,"guardianAttributes":0,"lightAbilities":0,"damageTypes":0},"trueStepIndex":0,"truePropertyIndex":0,"affectsLevel":false},{"stepIndex":1,"nodeStepHash":1528865420,"nodeStepName":"\u30cf\u30fc\u30c9\u30b7\u30e7\u30c3\u30c8","nodeStepDescription":"\u901f\u5ea6\u3068\u7206\u767a\u7bc4\u56f2\u3092\u5f37\u5316\u3059\u308b\u3002\n\u53cd\u52d5\u304c\u5927\u304d\u304f\u306a\u308b\u3002","interactionDescription":"\u30a2\u30c3\u30d7\u30b0\u30ec\u30fc\u30c9","icon":"\/common\/destiny_content\/icons\/5f850325aadf7b61a78342fc9d30687c.png","damageType":0,"activationRequirement":{"gridLevel":4,"materialRequirementHashes":[2949229212]},"canActivateNextStep":false,"nextStepIndex":-1,"isNextStepRandom":true,"perkHashes":[2868044506],"startProgressionBarAtProgress":22500,"statHashes":[2523465841,3614673599,155624089],"affectsQuality":false,"stepGroups":{"weaponPerformance":1056,"impactEffects":0,"guardianAttributes":0,"lightAbilities":0,"damageTypes":0},"trueStepIndex":0,"truePropertyIndex":0,"affectsLevel":false}],"exlusiveWithNodes":[312682976,452419628],"randomStartProgressionBarAtProgression":0},{"nodeIndex":8,"nodeHash":3359939809,"row":0,"column":4,"prerequisiteNodeIndexes":[],"binaryPairNodeIndex":-1,"autoUnlocks":false,"lastStepRepeats":false,"isRandom":true,"randomActivationRequirement":{"gridLevel":0},"isRandomRepurchasable":false,"steps":[{"stepIndex":0,"nodeStepHash":2623937842,"nodeStepName":"\u30af\u30a4\u30c3\u30af\u30c9\u30ed\u30fc","nodeStepDescription":"\u6b66\u5668\u3092\u9a5a\u304f\u307b\u3069\u306e\u901f\u3055\u3067\u69cb\u3048\u3089\u308c\u308b\u3002","interactionDescription":"\u30a2\u30c3\u30d7\u30b0\u30ec\u30fc\u30c9","icon":"\/common\/destiny_content\/icons\/cd3bcdfe4fb089e6b57f56ecb8f04cf1.png","damageType":0,"activationRequirement":{"gridLevel":5,"materialRequirementHashes":[391095254]},"canActivateNextStep":false,"nextStepIndex":-1,"isNextStepRandom":true,"perkHashes":[1318606268],"startProgressionBarAtProgress":37500,"statHashes":[],"affectsQuality":false,"stepGroups":{"weaponPerformance":128,"impactEffects":0,"guardianAttributes":0,"lightAbilities":0,"damageTypes":0},"trueStepIndex":0,"truePropertyIndex":0,"affectsLevel":false},{"stepIndex":1,"nodeStepHash":2364201573,"nodeStepName":"\u30d1\u30fc\u30d5\u30a7\u30af\u30c8\u30d0\u30e9\u30f3\u30b9","nodeStepDescription":"\u6b66\u5668\u306e\u53cd\u52d5\u304c\u6975\u9650\u307e\u3067\u4f4e\u4e0b\u3059\u308b\u3002","interactionDescription":"\u30a2\u30c3\u30d7\u30b0\u30ec\u30fc\u30c9","icon":"\/common\/destiny_content\/icons\/c3e046769007f47035b3e0abb2e8f92e.png","damageType":0,"activationRequirement":{"gridLevel":5,"materialRequirementHashes":[391095254]},"canActivateNextStep":false,"nextStepIndex":-1,"isNextStepRandom":true,"perkHashes":[],"startProgressionBarAtProgress":37500,"statHashes":[155624089],"affectsQuality":false,"stepGroups":{"weaponPerformance":32,"impactEffects":0,"guardianAttributes":0,"lightAbilities":0,"damageTypes":0},"trueStepIndex":0,"truePropertyIndex":0,"affectsLevel":false},{"stepIndex":2,"nodeStepHash":2202667868,"nodeStepName":"\u30d5\u30a3\u30c3\u30c8\u30b9\u30c8\u30c3\u30af","nodeStepDescription":"\u6b66\u5668\u306e\u5b89\u5b9a\u6027\u304c\u5411\u4e0a\u3059\u308b\u3002","interactionDescription":"\u30a2\u30c3\u30d7\u30b0\u30ec\u30fc\u30c9","icon":"\/common\/destiny_content\/icons\/20b4d406eb7ae0e4746aeccfcbaef2ef.png","damageType":0,"activationRequirement":{"gridLevel":5,"materialRequirementHashes":[391095254]},"canActivateNextStep":false,"nextStepIndex":-1,"isNextStepRandom":true,"perkHashes":[],"startProgressionBarAtProgress":37500,"statHashes":[155624089],"affectsQuality":false,"stepGroups":{"weaponPerformance":32,"impactEffects":0,"guardianAttributes":0,"lightAbilities":0,"damageTypes":0},"trueStepIndex":0,"truePropertyIndex":0,"affectsLevel":false}],"exlusiveWithNodes":[3872169477,2947148901],"randomStartProgressionBarAtProgression":0},{"nodeIndex":9,"nodeHash":2947148901,"row":1,"column":4,"prerequisiteNodeIndexes":[],"binaryPairNodeIndex":-1,"autoUnlocks":false,"lastStepRepeats":false,"isRandom":true,"randomActivationRequirement":{"gridLevel":0},"isRandomRepurchasable":false,"steps":[{"stepIndex":0,"nodeStepHash":31986388,"nodeStepName":"\u30d8\u30d3\u30fc\u30da\u30a4\u30ed\u30fc\u30c9","nodeStepDescription":"\u5f3e\u306e\u7206\u767a\u7bc4\u56f2\u304c\u62e1\u5927\u3059\u308b\u3002","interactionDescription":"\u30a2\u30c3\u30d7\u30b0\u30ec\u30fc\u30c9","icon":"\/common\/destiny_content\/icons\/27ef23377893d56f4fb02f1e8756b296.png","damageType":0,"activationRequirement":{"gridLevel":6,"materialRequirementHashes":[391095254]},"canActivateNextStep":false,"nextStepIndex":-1,"isNextStepRandom":true,"perkHashes":[],"startProgressionBarAtProgress":52500,"statHashes":[3614673599],"affectsQuality":false,"stepGroups":{"weaponPerformance":1024,"impactEffects":0,"guardianAttributes":0,"lightAbilities":0,"damageTypes":0},"trueStepIndex":0,"truePropertyIndex":0,"affectsLevel":false},{"stepIndex":1,"nodeStepHash":291722657,"nodeStepName":"\u30d5\u30ec\u30a2\u30de\u30b0\u30a6\u30a7\u30eb","nodeStepDescription":"\u30ea\u30ed\u30fc\u30c9\u304c\u3055\u3089\u306b\u901f\u304f\u306a\u308b\u3002","interactionDescription":"\u30a2\u30c3\u30d7\u30b0\u30ec\u30fc\u30c9","icon":"\/common\/destiny_content\/icons\/6976dbbedd7305f8e460d8ef1f35179d.png","damageType":0,"activationRequirement":{"gridLevel":6,"materialRequirementHashes":[391095254]},"canActivateNextStep":false,"nextStepIndex":-1,"isNextStepRandom":true,"perkHashes":[],"startProgressionBarAtProgress":52500,"statHashes":[4188031367],"affectsQuality":false,"stepGroups":{"weaponPerformance":128,"impactEffects":0,"guardianAttributes":0,"lightAbilities":0,"damageTypes":0},"trueStepIndex":0,"truePropertyIndex":0,"affectsLevel":false},{"stepIndex":2,"nodeStepHash":2981876675,"nodeStepName":"\u30b7\u30f3\u30b0\u30eb\u30dd\u30a4\u30f3\u30c8\u30fb\u30b9\u30ea\u30f3\u30b0","nodeStepDescription":"\u6b66\u5668\u306e\u6301\u3061\u66ff\u3048\u304c\u901f\u304f\u306a\u308b\u3002\u72d9\u3063\u3066\u3044\u308b\u6642\u306e\u79fb\u52d5\u901f\u5ea6\u3082\u901f\u304f\u306a\u308b\u3002","interactionDescription":"\u30a2\u30c3\u30d7\u30b0\u30ec\u30fc\u30c9","icon":"\/common\/destiny_content\/icons\/e695e8e3606ccf005f25a838b654ebca.png","damageType":0,"activationRequirement":{"gridLevel":6,"materialRequirementHashes":[391095254]},"canActivateNextStep":false,"nextStepIndex":-1,"isNextStepRandom":true,"perkHashes":[1543923140],"startProgressionBarAtProgress":52500,"statHashes":[],"affectsQuality":false,"stepGroups":{"weaponPerformance":64,"impactEffects":0,"guardianAttributes":0,"lightAbilities":0,"damageTypes":0},"trueStepIndex":0,"truePropertyIndex":0,"affectsLevel":false}],"exlusiveWithNodes":[3872169477,3359939809],"randomStartProgressionBarAtProgression":0},{"nodeIndex":10,"nodeHash":486779184,"row":0,"column":7,"prerequisiteNodeIndexes":[],"binaryPairNodeIndex":-1,"autoUnlocks":false,"lastStepRepeats":false,"isRandom":false,"isRandomRepurchasable":false,"steps":[{"stepIndex":0,"nodeStepHash":1277492283,"nodeStepName":"\u30c0\u30e1\u30fc\u30b8\u5f37\u5316","nodeStepDescription":"\u3053\u306e\u6b66\u5668\u306e\u653b\u6483\u529b\u3092\u4e0a\u6607\u3055\u305b\u3066\u4e0e\u3048\u308b\u30c0\u30e1\u30fc\u30b8\u3092\u5897\u52a0\u3055\u305b\u308b\u3002","interactionDescription":"\u30a2\u30c3\u30d7\u30b0\u30ec\u30fc\u30c9","icon":"\/common\/destiny_content\/icons\/2c564a7f220855661066d6a308940940.png","damageType":0,"activationRequirement":{"gridLevel":9,"materialRequirementHashes":[3984507349,3984507348,3984507351,3984507350]},"canActivateNextStep":false,"nextStepIndex":-1,"isNextStepRandom":false,"perkHashes":[],"startProgressionBarAtProgress":97500,"statHashes":[],"affectsQuality":true,"trueStepIndex":0,"truePropertyIndex":0,"affectsLevel":false}],"exlusiveWithNodes":[],"randomStartProgressionBarAtProgression":0},{"nodeIndex":11,"nodeHash":1560693961,"row":1,"column":7,"prerequisiteNodeIndexes":[],"binaryPairNodeIndex":-1,"autoUnlocks":false,"lastStepRepeats":false,"isRandom":false,"isRandomRepurchasable":false,"steps":[{"stepIndex":0,"nodeStepHash":4227382570,"nodeStepName":"\u30c0\u30e1\u30fc\u30b8\u5f37\u5316","nodeStepDescription":"\u3053\u306e\u6b66\u5668\u306e\u653b\u6483\u529b\u3092\u4e0a\u6607\u3055\u305b\u3066\u4e0e\u3048\u308b\u30c0\u30e1\u30fc\u30b8\u3092\u5897\u52a0\u3055\u305b\u308b\u3002","interactionDescription":"\u30a2\u30c3\u30d7\u30b0\u30ec\u30fc\u30c9","icon":"\/common\/destiny_content\/icons\/2c564a7f220855661066d6a308940940.png","damageType":0,"activationRequirement":{"gridLevel":10,"materialRequirementHashes":[3984507349,3984507348,3984507351,3984507350]},"canActivateNextStep":false,"nextStepIndex":-1,"isNextStepRandom":false,"perkHashes":[],"startProgressionBarAtProgress":112500,"statHashes":[],"affectsQuality":true,"trueStepIndex":0,"truePropertyIndex":0,"affectsLevel":false}],"exlusiveWithNodes":[],"randomStartProgressionBarAtProgression":0},{"nodeIndex":12,"nodeHash":1560841054,"row":2,"column":7,"prerequisiteNodeIndexes":[],"binaryPairNodeIndex":-1,"autoUnlocks":false,"lastStepRepeats":false,"isRandom":false,"isRandomRepurchasable":false,"steps":[{"stepIndex":0,"nodeStepHash":2882305561,"nodeStepName":"\u30c0\u30e1\u30fc\u30b8\u5f37\u5316","nodeStepDescription":"\u3053\u306e\u6b66\u5668\u306e\u653b\u6483\u529b\u3092\u4e0a\u6607\u3055\u305b\u3066\u4e0e\u3048\u308b\u30c0\u30e1\u30fc\u30b8\u3092\u5897\u52a0\u3055\u305b\u308b\u3002","interactionDescription":"\u30a2\u30c3\u30d7\u30b0\u30ec\u30fc\u30c9","icon":"\/common\/destiny_content\/icons\/2c564a7f220855661066d6a308940940.png","damageType":0,"activationRequirement":{"gridLevel":11,"materialRequirementHashes":[3984507349,3984507348,3984507351,3984507350]},"canActivateNextStep":false,"nextStepIndex":-1,"isNextStepRandom":false,"perkHashes":[],"startProgressionBarAtProgress":127500,"statHashes":[],"affectsQuality":true,"trueStepIndex":0,"truePropertyIndex":0,"affectsLevel":false}],"exlusiveWithNodes":[],"randomStartProgressionBarAtProgression":0},{"nodeIndex":13,"nodeHash":99489719,"row":0,"column":6,"prerequisiteNodeIndexes":[],"binaryPairNodeIndex":-1,"autoUnlocks":false,"lastStepRepeats":false,"isRandom":false,"isRandomRepurchasable":false,"steps":[{"stepIndex":0,"nodeStepHash":491986635,"nodeStepName":"\u30c0\u30e1\u30fc\u30b8\u5f37\u5316","nodeStepDescription":"\u3053\u306e\u6b66\u5668\u306e\u653b\u6483\u529b\u3092\u4e0a\u6607\u3055\u305b\u3066\u4e0e\u3048\u308b\u30c0\u30e1\u30fc\u30b8\u3092\u5897\u52a0\u3055\u305b\u308b\u3002","interactionDescription":"\u30a2\u30c3\u30d7\u30b0\u30ec\u30fc\u30c9","icon":"\/common\/destiny_content\/icons\/2c564a7f220855661066d6a308940940.png","damageType":0,"activationRequirement":{"gridLevel":8,"materialRequirementHashes":[3984475350,3984475351,3984475348,3984475349]},"canActivateNextStep":false,"nextStepIndex":-1,"isNextStepRandom":false,"perkHashes":[],"startProgressionBarAtProgress":67500,"statHashes":[],"affectsQuality":true,"trueStepIndex":0,"truePropertyIndex":0,"affectsLevel":false}],"exlusiveWithNodes":[],"randomStartProgressionBarAtProgression":0}],"calcMaxGridLevel":0,"calcProgressToMaxLevel":0}},"definitions":{"destinations":{},"places":{},"activityTypes":{},"items":{},"buckets":{"953998645":{"bucketHash":953998645,"bucketName":"\u30d8\u30d3\u30fc\u30a6\u30a7\u30dd\u30f3","bucketDescription":"\u30de\u30b7\u30f3\u30ac\u30f3\u3068\u30ed\u30b1\u30c3\u30c8\u30e9\u30f3\u30c1\u30e3\u30fc","scope":0,"category":3,"bucketOrder":4,"bucketIdentifier":"BUCKET_HEAVY_WEAPON","itemCount":10,"location":1,"hasTransferDestination":true}},"stats":{"368428387":{"statHash":368428387,"statName":"\u653b\u6483\u529b","statDescription":"\u653b\u6483\u529b\u3092\u4e0a\u6607\u3055\u305b\u308b\u3068\u3001\u9ad8\u30ec\u30d9\u30eb\u306e\u6575\u306b\u6b66\u5668\u3067\u30c0\u30e1\u30fc\u30b8\u3092\u4e0e\u3048\u3089\u308c\u308b\u3088\u3046\u306b\u306a\u308b\u3002","icon":"\/img\/misc\/missing_icon.png","statIdentifier":"STAT_DAMAGE","interpolate":false},"3555269338":{"statHash":3555269338,"statName":"\u5149\u5b66\u7167\u6e96\u5668","statDescription":"\u5149\u5b66\u30ba\u30fc\u30e0\u5206\u5272","icon":"\/img\/misc\/missing_icon.png","statIdentifier":"STAT_OPTICS","interpolate":false},"4284893193":{"statHash":4284893193,"statName":"\u9023\u5c04\u901f\u5ea6","statDescription":"1\u5206\u9593\u306b\u3064\u304d\u767a\u5c04\u3067\u304d\u308b\u5f3e\u306e\u6570\u3002","icon":"\/img\/misc\/missing_icon.png","statIdentifier":"STAT_RATE_OF_FIRE","interpolate":false},"3614673599":{"statHash":3614673599,"statName":"\u7206\u767a\u7bc4\u56f2","statDescription":"\u3053\u306e\u6b66\u5668\u306e\u7206\u767a\u7bc4\u56f2\u3092\u5897\u52a0\u3055\u305b\u308b\u3002","icon":"\/img\/misc\/missing_icon.png","statIdentifier":"STAT_BLAST_RADIUS","interpolate":false},"2523465841":{"statHash":2523465841,"statName":"\u901f\u5ea6","statDescription":"\u3053\u306e\u6b66\u5668\u304b\u3089\u767a\u5c04\u3055\u308c\u308b\u6295\u5c04\u7269\u306e\u901f\u5ea6\u3092\u5897\u52a0\u3055\u305b\u308b\u3002","icon":"\/img\/misc\/missing_icon.png","statIdentifier":"STAT_PROJECTILE_SPEED","interpolate":false},"155624089":{"statHash":155624089,"statName":"\u5b89\u5b9a\u6027","statDescription":"\u9023\u7d9a\u5c04\u6483\u6642\u306e\u6b66\u5668\u306e\u53cd\u52d5\u3092\u6e1b\u5c11\u3055\u305b\u308b\u3002","icon":"\/img\/misc\/missing_icon.png","statIdentifier":"STAT_STABILITY","interpolate":false},"3871231066":{"statHash":3871231066,"statName":"\u30de\u30ac\u30b8\u30f3","statDescription":"\u30ea\u30ed\u30fc\u30c9\u305b\u305a\u306b\u6483\u3066\u308b\u56de\u6570\u3002","icon":"\/img\/misc\/missing_icon.png","statIdentifier":"STAT_MAGAZINE_SIZE","interpolate":false},"4188031367":{"statHash":4188031367,"statName":"\u30ea\u30ed\u30fc\u30c9","statDescription":"\u6b66\u5668\u306e\u30ea\u30ed\u30fc\u30c9\u306b\u304b\u304b\u308b\u6642\u9593\u3092\u6e1b\u5c11\u3055\u305b\u308b\u3002","icon":"\/img\/misc\/missing_icon.png","statIdentifier":"STAT_RELOAD","interpolate":false},"1931675084":{"statHash":1931675084,"statName":"\u6240\u6301\u54c1\u306e\u30b5\u30a4\u30ba","statDescription":"\u6240\u6301\u54c1\u3067\u6b66\u5668\u304c\u5360\u3081\u3066\u3044\u308b\u91cf\u3002","icon":"\/img\/misc\/missing_icon.png","statIdentifier":"STAT_INVENTORY_SIZE","interpolate":false},"943549884":{"statHash":943549884,"statName":"\u88c5\u5099\u30b9\u30d4\u30fc\u30c9","statDescription":"\u6b66\u5668\u3092\u69cb\u3048\u3001\u72d9\u3044\u3092\u5b9a\u3081\u308b\u307e\u3067\u306e\u30b9\u30d4\u30fc\u30c9\u3002","icon":"\/img\/misc\/missing_icon.png","statIdentifier":"STAT_EQUIP_SPEED","interpolate":false},"1345609583":{"statHash":1345609583,"statName":"\u30a8\u30a4\u30e0\u30a2\u30b7\u30b9\u30c8","statDescription":"\u547d\u4e2d\u7cbe\u5ea6\u3092\u4e0a\u6607\u3055\u305b\u308b\u6b66\u5668\u30b9\u30ad\u30eb\u3002","icon":"\/img\/misc\/missing_icon.png","statIdentifier":"STAT_AIM_ASSISTANCE","interpolate":false},"2715839340":{"statHash":2715839340,"statName":"\u53cd\u52d5\u65b9\u5411","statDescription":"\u6483\u3063\u3066\u3044\u308b\u6642\u306b\u6b66\u5668\u304c\u52d5\u304d\u3084\u3059\u3044\u65b9\u5411\u3002","icon":"\/img\/misc\/missing_icon.png","statIdentifier":"STAT_RECOIL_DIRECTION","interpolate":false}},"perks":{"3453522274":{"perkHash":3453522274,"displayIcon":"\/img\/misc\/missing_icon.png","isDisplayable":false},"805224273":{"perkHash":805224273,"displayIcon":"\/img\/misc\/missing_icon.png","isDisplayable":false},"3614988247":{"perkHash":3614988247,"displayIcon":"\/img\/misc\/missing_icon.png","perkIdentifier":"PERK_VOID_DAMAGE","isDisplayable":false,"perkGroups":{"weaponPerformance":0,"impactEffects":0,"guardianAttributes":0,"lightAbilities":0,"damageTypes":8}},"233596484":{"perkHash":233596484,"displayIcon":"\/img\/misc\/missing_icon.png","perkIdentifier":"PERK_THERMAL_DAMAGE","isDisplayable":false,"perkGroups":{"weaponPerformance":0,"impactEffects":0,"guardianAttributes":0,"lightAbilities":0,"damageTypes":4}},"839929915":{"perkHash":839929915,"displayIcon":"\/img\/misc\/missing_icon.png","perkIdentifier":"PERK_ARC_DAMAGE","isDisplayable":false,"perkGroups":{"weaponPerformance":0,"impactEffects":0,"guardianAttributes":0,"lightAbilities":0,"damageTypes":2}},"2868044506":{"perkHash":2868044506,"displayIcon":"\/img\/misc\/missing_icon.png","isDisplayable":false},"1563623317":{"perkHash":1563623317,"displayIcon":"\/img\/misc\/missing_icon.png","isDisplayable":false,"perkGroups":{"weaponPerformance":64,"impactEffects":0,"guardianAttributes":0,"lightAbilities":0,"damageTypes":0}},"3052118152":{"perkHash":3052118152,"displayName":"\u30af\u30e9\u30a6\u30f3\u30fb\u30ab\u30fc\u30c8\u30ea\u30c3\u30b8","displayDescription":"\u30ea\u30ed\u30fc\u30c9\u3059\u308b\u3068\u3001\u4e00\u5b9a\u306e\u78ba\u7387\u3067\u901a\u5e38\u3088\u308a\u5927\u304d\u306a\u30de\u30ac\u30b8\u30f3\u3092\u7372\u5f97\u3067\u304d\u308b\u3002","displayIcon":"\/img\/misc\/missing_icon.png","isDisplayable":true,"perkGroups":{"weaponPerformance":512,"impactEffects":0,"guardianAttributes":0,"lightAbilities":0,"damageTypes":0}},"3283108368":{"perkHash":3283108368,"displayName":"\u30b0\u30ec\u30cd\u30fc\u30c0\u30fc","displayDescription":"\u6575\u3092\u5012\u3059\u3068\u3001\u30b0\u30ec\u30cd\u30fc\u30c9\u306e\u30af\u30fc\u30eb\u30c0\u30a6\u30f3\u6642\u9593\u304c\u77ed\u7e2e\u3055\u308c\u308b\u3002","displayIcon":"\/img\/misc\/missing_icon.png","isDisplayable":true,"perkGroups":{"weaponPerformance":0,"impactEffects":0,"guardianAttributes":0,"lightAbilities":1,"damageTypes":0}},"1989386514":{"perkHash":1989386514,"displayName":"\u5438\u5f15","displayDescription":"\u3053\u306e\u6b66\u5668\u306e\u843d\u3061\u3066\u3044\u308b\u5f3e\u4e38\u306e\u56de\u53ce\u7bc4\u56f2\u304c\u5e83\u304f\u306a\u308b\u3002","displayIcon":"\/img\/misc\/missing_icon.png","isDisplayable":true,"perkGroups":{"weaponPerformance":512,"impactEffects":0,"guardianAttributes":0,"lightAbilities":0,"damageTypes":0}},"192233393":{"perkHash":192233393,"displayName":"\u30b9\u30d4\u30fc\u30c9\u30d7\u30ec\u30a4","displayDescription":"\u3053\u306e\u6b66\u5668\u306e\u9283\u5009\u304c\u7a7a\u306b\u306a\u3063\u305f\u6642\u306e\u30ea\u30ed\u30fc\u30c9\u901f\u5ea6\u304c\u4e0a\u304c\u308b\u3002","displayIcon":"\/img\/misc\/missing_icon.png","isDisplayable":true,"perkGroups":{"weaponPerformance":128,"impactEffects":0,"guardianAttributes":0,"lightAbilities":0,"damageTypes":0}},"770631416":{"perkHash":770631416,"displayName":"\u7b2c\u4e09\u306e\u76ee","displayDescription":"\u3053\u306e\u7167\u6e96\u5668\u3067\u72d9\u3044\u3092\u5b9a\u3081\u3066\u3044\u308b\u9593\u3001\u30ec\u30fc\u30c0\u30fc\u304c\u6709\u52b9\u306b\u306a\u308b\u3002","displayIcon":"\/img\/misc\/missing_icon.png","isDisplayable":true,"perkGroups":{"weaponPerformance":0,"impactEffects":0,"guardianAttributes":32,"lightAbilities":0,"damageTypes":0}},"3686406336":{"perkHash":3686406336,"displayName":"\u30d5\u30fc\u30ba\u30fb\u30cd\u30af\u30b9\u30c8","displayDescription":"\u30de\u30ac\u30b8\u30f3\u306e\u6700\u5f8c\u306e\u4e00\u767a\u3067\u6575\u3092\u5012\u3059\u3068\u3001\u30ea\u30ed\u30fc\u30c9\u901f\u5ea6\u304c\u4e0a\u6607\u3059\u308b\u3002","displayIcon":"\/img\/misc\/missing_icon.png","isDisplayable":true,"perkGroups":{"weaponPerformance":128,"impactEffects":0,"guardianAttributes":0,"lightAbilities":0,"damageTypes":0}},"1928591453":{"perkHash":1928591453,"displayName":"\u30af\u30e9\u30b9\u30bf\u30fc\u7206\u5f3e","displayDescription":"\u30ed\u30b1\u30c3\u30c8\u304c\u7206\u767a\u3059\u308b\u6642\u306b\u30af\u30e9\u30b9\u30bf\u30fc\u7206\u5f3e\u304c\u751f\u6210\u3055\u308c\u308b\u3002","displayIcon":"\/img\/misc\/missing_icon.png","isDisplayable":true,"perkGroups":{"weaponPerformance":1026,"impactEffects":8,"guardianAttributes":0,"lightAbilities":0,"damageTypes":0}},"2425591494":{"perkHash":2425591494,"displayName":"\u30b0\u30ec\u30cd\u30fc\u30c9&\u30db\u30fc\u30b9\u30b7\u30e5\u30fc\u30ba","displayDescription":"\u767a\u5c04\u3057\u305f\u30ed\u30b1\u30c3\u30c8\u304c\u6a19\u7684\u3068\u306e\u8ddd\u96e2\u306b\u5fdc\u3058\u3066\u65e9\u3081\u306b\u7206\u767a\u3059\u308b\u3002","displayIcon":"\/img\/misc\/missing_icon.png","isDisplayable":true,"perkGroups":{"weaponPerformance":1024,"impactEffects":0,"guardianAttributes":0,"lightAbilities":0,"damageTypes":0}},"2626112550":{"perkHash":2626112550,"displayName":"\u5c48\u5f37","displayDescription":"\u3053\u306e\u6b66\u5668\u3092\u4f7f\u7528\u3059\u308b\u3068\u3001\u653b\u6483\u3092\u53d7\u3051\u3066\u308b\u9593\u3082\u72d9\u3044\u3092\u3064\u3051\u3084\u3059\u304f\u306a\u308b\u3002","displayIcon":"\/img\/misc\/missing_icon.png","isDisplayable":true,"perkGroups":{"weaponPerformance":0,"impactEffects":0,"guardianAttributes":16,"lightAbilities":0,"damageTypes":0}},"824061322":{"perkHash":824061322,"displayName":"\u30de\u30ea\u30ac\u30f3","displayDescription":"\u547d\u4e2d\u3057\u306a\u304b\u3063\u305f\u5f3e\u304c\u4e00\u5b9a\u306e\u78ba\u7387\u3067\u76f4\u63a5\u30de\u30ac\u30b8\u30f3\u306b\u623b\u308b\u3002","displayIcon":"\/img\/misc\/missing_icon.png","isDisplayable":true,"perkGroups":{"weaponPerformance":512,"impactEffects":0,"guardianAttributes":0,"lightAbilities":0,"damageTypes":0}},"3317503477":{"perkHash":3317503477,"displayName":"\u30b5\u30fc\u30d7\u30e9\u30b9","displayDescription":"\u843d\u3061\u3066\u3044\u308b\u5f3e\u85ac\u3092\u767a\u898b\u3057\u3084\u3059\u304f\u306a\u308b\u3002","displayIcon":"\/img\/misc\/missing_icon.png","isDisplayable":true,"perkGroups":{"weaponPerformance":512,"impactEffects":0,"guardianAttributes":0,"lightAbilities":0,"damageTypes":0}},"2784842908":{"perkHash":2784842908,"displayName":"\u30c8\u30e9\u30a4\u30dd\u30c3\u30c9","displayDescription":"\u3053\u306e\u30e9\u30f3\u30c1\u30e3\u30fc\u306f3\u767a\u307e\u3067\u5f3e\u3092\u88c5\u586b\u3067\u304d\u308b\u3002","displayIcon":"\/img\/misc\/missing_icon.png","isDisplayable":true,"perkGroups":{"weaponPerformance":512,"impactEffects":0,"guardianAttributes":0,"lightAbilities":0,"damageTypes":0}},"2179933840":{"perkHash":2179933840,"displayName":"\u30c8\u30e9\u30c3\u30ad\u30f3\u30b0","displayDescription":"\u30db\u30fc\u30df\u30f3\u30b0\u5f3e\u3092\u6483\u3066\u308b\u3002","displayIcon":"\/img\/misc\/missing_icon.png","isDisplayable":true,"perkGroups":{"weaponPerformance":1024,"impactEffects":0,"guardianAttributes":0,"lightAbilities":0,"damageTypes":0}},"3097446979":{"perkHash":3097446979,"displayIcon":"\/img\/misc\/missing_icon.png","isDisplayable":false},"2272440440":{"perkHash":2272440440,"displayIcon":"\/img\/misc\/missing_icon.png","isDisplayable":false},"1318606268":{"perkHash":1318606268,"displayIcon":"\/img\/misc\/missing_icon.png","isDisplayable":false,"perkGroups":{"weaponPerformance":128,"impactEffects":0,"guardianAttributes":0,"lightAbilities":0,"damageTypes":0}},"1543923140":{"perkHash":1543923140,"displayIcon":"\/img\/misc\/missing_icon.png","isDisplayable":false,"perkGroups":{"weaponPerformance":64,"impactEffects":0,"guardianAttributes":0,"lightAbilities":0,"damageTypes":0}}},"talentGrids":{"3821688456":{"gridHash":3821688456,"maxGridLevel":0,"gridLevelPerColumn":0,"progressionHash":1054627247,"nodes":[{"nodeIndex":0,"nodeHash":402641165,"row":0,"column":0,"prerequisiteNodeIndexes":[],"binaryPairNodeIndex":-1,"autoUnlocks":true,"lastStepRepeats":false,"isRandom":true,"randomActivationRequirement":{"gridLevel":0},"isRandomRepurchasable":false,"steps":[{"stepIndex":0,"nodeStepHash":4134271514,"nodeStepName":"\u30dc\u30a4\u30c9\u30fb\u30c0\u30e1\u30fc\u30b8","nodeStepDescription":"\u30dc\u30a4\u30c9\u30fb\u30c0\u30e1\u30fc\u30b8\u3092\u4e0e\u3048\u308b\u3002","interactionDescription":"\u30ea\u30ed\u30fc\u30eb","icon":"\/common\/destiny_content\/icons\/bc527dbbeed646129dbda1a29f719fc3.png","damageType":4,"activationRequirement":{"gridLevel":0,"materialRequirementHashes":[]},"canActivateNextStep":false,"nextStepIndex":-1,"isNextStepRandom":true,"perkHashes":[3614988247],"startProgressionBarAtProgress":0,"statHashes":[],"affectsQuality":false,"stepGroups":{"weaponPerformance":0,"impactEffects":0,"guardianAttributes":0,"lightAbilities":0,"damageTypes":8},"trueStepIndex":0,"truePropertyIndex":0,"affectsLevel":false},{"stepIndex":1,"nodeStepHash":2093640965,"nodeStepName":"\u30bd\u30fc\u30e9\u30fc\u30c0\u30e1\u30fc\u30b8","nodeStepDescription":"\u30bd\u30fc\u30e9\u30fc\u30c0\u30e1\u30fc\u30b8\u3092\u4e0e\u3048\u308b\u3002","interactionDescription":"\u30ea\u30ed\u30fc\u30eb","icon":"\/common\/destiny_content\/icons\/c2fad8059225eed26742c4b293f424ec.png","damageType":3,"activationRequirement":{"gridLevel":0,"materialRequirementHashes":[]},"canActivateNextStep":false,"nextStepIndex":-1,"isNextStepRandom":true,"perkHashes":[233596484],"startProgressionBarAtProgress":0,"statHashes":[],"affectsQuality":false,"stepGroups":{"weaponPerformance":0,"impactEffects":0,"guardianAttributes":0,"lightAbilities":0,"damageTypes":4},"trueStepIndex":0,"truePropertyIndex":0,"affectsLevel":false},{"stepIndex":2,"nodeStepHash":1859696124,"nodeStepName":"\u30a2\u30fc\u30af\u30fb\u30c0\u30e1\u30fc\u30b8","nodeStepDescription":"\u30a2\u30fc\u30af\u30fb\u30c0\u30e1\u30fc\u30b8\u3092\u4e0e\u3048\u308b\u3002","interactionDescription":"\u30ea\u30ed\u30fc\u30eb","icon":"\/common\/destiny_content\/icons\/2a7123978a4da00f33e456fef6e9065a.png","damageType":2,"activationRequirement":{"gridLevel":0,"materialRequirementHashes":[]},"canActivateNextStep":false,"nextStepIndex":-1,"isNextStepRandom":true,"perkHashes":[839929915],"startProgressionBarAtProgress":0,"statHashes":[],"affectsQuality":false,"stepGroups":{"weaponPerformance":0,"impactEffects":0,"guardianAttributes":0,"lightAbilities":0,"damageTypes":2},"trueStepIndex":0,"truePropertyIndex":0,"affectsLevel":false}],"exlusiveWithNodes":[],"randomStartProgressionBarAtProgression":0},{"nodeIndex":1,"nodeHash":312682976,"row":1,"column":1,"prerequisiteNodeIndexes":[],"binaryPairNodeIndex":-1,"autoUnlocks":false,"lastStepRepeats":false,"isRandom":true,"randomActivationRequirement":{"gridLevel":0},"isRandomRepurchasable":false,"steps":[{"stepIndex":0,"nodeStepHash":4219019438,"nodeStepName":"\u30bd\u30d5\u30c8\u30b7\u30e7\u30c3\u30c8","nodeStepDescription":"\u53cd\u52d5\u3092\u8efd\u6e1b\u3059\u308b\u3002\n\u305f\u3060\u3057\u901f\u5ea6\u304c\u843d\u3061\u308b\u3002","interactionDescription":"\u30a2\u30c3\u30d7\u30b0\u30ec\u30fc\u30c9","icon":"\/common\/destiny_content\/icons\/5f850325aadf7b61a78342fc9d30687c.png","damageType":0,"activationRequirement":{"gridLevel":3,"materialRequirementHashes":[2949229212]},"canActivateNextStep":false,"nextStepIndex":-1,"isNextStepRandom":true,"perkHashes":[],"startProgressionBarAtProgress":7500,"statHashes":[2523465841,155624089],"affectsQuality":false,"stepGroups":{"weaponPerformance":32,"impactEffects":0,"guardianAttributes":0,"lightAbilities":0,"damageTypes":0},"trueStepIndex":0,"truePropertyIndex":0,"affectsLevel":false},{"stepIndex":1,"nodeStepHash":183788411,"nodeStepName":"\u30ea\u30cb\u30a2\u30fb\u30b3\u30f3\u30da\u30f3\u30bb\u30a4\u30bf\u30fc","nodeStepDescription":"\u53cd\u52d5\u304c\u898f\u5247\u7684\u306b\u306a\u308b\u3002\n\u901f\u5ea6\u3068\u7206\u767a\u7bc4\u56f2\u3092\u308f\u305a\u304b\u306b\u5f37\u5316\u3059\u308b\u3002\n\u53cd\u52d5\u306f\u5927\u304d\u304f\u306a\u308b\u3002","interactionDescription":"\u30a2\u30c3\u30d7\u30b0\u30ec\u30fc\u30c9","icon":"\/common\/destiny_content\/icons\/5f850325aadf7b61a78342fc9d30687c.png","damageType":0,"activationRequirement":{"gridLevel":3,"materialRequirementHashes":[2949229212]},"canActivateNextStep":false,"nextStepIndex":-1,"isNextStepRandom":true,"perkHashes":[2868044506],"startProgressionBarAtProgress":7500,"statHashes":[2523465841,3614673599,2715839340,155624089],"affectsQuality":false,"stepGroups":{"weaponPerformance":1056,"impactEffects":0,"guardianAttributes":0,"lightAbilities":0,"damageTypes":0},"trueStepIndex":0,"truePropertyIndex":0,"affectsLevel":false},{"stepIndex":2,"nodeStepHash":443524680,"nodeStepName":"\u30b9\u30de\u30fc\u30c8\u30fb\u30c9\u30ea\u30d5\u30c8\u30fb\u30b3\u30f3\u30c8\u30ed\u30fc\u30eb","nodeStepDescription":"\u898f\u5247\u7684\u306a\u53cd\u52d5\u3067\u5236\u5fa1\u3057\u3084\u3059\u304f\u306a\u308b\u3002\n\u901f\u5ea6\u304c\u843d\u3061\u308b\u3002","interactionDescription":"\u30a2\u30c3\u30d7\u30b0\u30ec\u30fc\u30c9","icon":"\/common\/destiny_content\/icons\/5f850325aadf7b61a78342fc9d30687c.png","damageType":0,"activationRequirement":{"gridLevel":3,"materialRequirementHashes":[2949229212]},"canActivateNextStep":false,"nextStepIndex":-1,"isNextStepRandom":true,"perkHashes":[],"startProgressionBarAtProgress":7500,"statHashes":[2523465841,2715839340,155624089],"affectsQuality":false,"stepGroups":{"weaponPerformance":32,"impactEffects":0,"guardianAttributes":0,"lightAbilities":0,"damageTypes":0},"trueStepIndex":0,"truePropertyIndex":0,"affectsLevel":false}],"exlusiveWithNodes":[452419628,1503756812],"randomStartProgressionBarAtProgression":0},{"nodeIndex":2,"nodeHash":3872169477,"row":2,"column":4,"prerequisiteNodeIndexes":[],"binaryPairNodeIndex":-1,"autoUnlocks":false,"lastStepRepeats":false,"isRandom":true,"randomActivationRequirement":{"gridLevel":0},"isRandomRepurchasable":false,"steps":[{"stepIndex":0,"nodeStepHash":3969014851,"nodeStepName":"\u30b9\u30ca\u30c3\u30d7\u30b7\u30e7\u30c3\u30c8","nodeStepDescription":"\u72d9\u3046\u901f\u3055\u304c\u6975\u7aef\u306b\u4e0a\u304c\u308b\u3002","interactionDescription":"\u30a2\u30c3\u30d7\u30b0\u30ec\u30fc\u30c9","icon":"\/common\/destiny_content\/icons\/ed61618f32ec01329a59ab37ea9934ce.png","damageType":0,"activationRequirement":{"gridLevel":7,"materialRequirementHashes":[391095254]},"canActivateNextStep":false,"nextStepIndex":-1,"isNextStepRandom":true,"perkHashes":[1563623317],"startProgressionBarAtProgress":67500,"statHashes":[],"affectsQuality":false,"stepGroups":{"weaponPerformance":64,"impactEffects":0,"guardianAttributes":0,"lightAbilities":0,"damageTypes":0},"trueStepIndex":0,"truePropertyIndex":0,"affectsLevel":false},{"stepIndex":1,"nodeStepHash":2104465304,"nodeStepName":"\u30b8\u30e3\u30d9\u30ea\u30f3","nodeStepDescription":"\u5f3e\u306e\u901f\u5ea6\u304c\u4e0a\u6607\u3059\u308b\u3002","interactionDescription":"\u30a2\u30c3\u30d7\u30b0\u30ec\u30fc\u30c9","icon":"\/common\/destiny_content\/icons\/5f850325aadf7b61a78342fc9d30687c.png","damageType":0,"activationRequirement":{"gridLevel":7,"materialRequirementHashes":[391095254]},"canActivateNextStep":false,"nextStepIndex":-1,"isNextStepRandom":true,"perkHashes":[],"startProgressionBarAtProgress":67500,"statHashes":[2523465841],"affectsQuality":false,"stepGroups":{"weaponPerformance":0,"impactEffects":0,"guardianAttributes":0,"lightAbilities":0,"damageTypes":0},"trueStepIndex":0,"truePropertyIndex":0,"affectsLevel":false},{"stepIndex":2,"nodeStepHash":3241612944,"nodeStepName":"\u30d5\u30a3\u30fc\u30eb\u30c9\u30b9\u30ab\u30a6\u30c8","nodeStepDescription":"\u5f3e\u4e38\u6700\u5927\u6570\u3002","interactionDescription":"\u30a2\u30c3\u30d7\u30b0\u30ec\u30fc\u30c9","icon":"\/common\/destiny_content\/icons\/0aeba7e8935ea9f58dd314faf4fc6018.png","damageType":0,"activationRequirement":{"gridLevel":7,"materialRequirementHashes":[391095254]},"canActivateNextStep":false,"nextStepIndex":-1,"isNextStepRandom":true,"perkHashes":[],"startProgressionBarAtProgress":67500,"statHashes":[3871231066,1931675084],"affectsQuality":false,"stepGroups":{"weaponPerformance":512,"impactEffects":0,"guardianAttributes":0,"lightAbilities":0,"damageTypes":0},"trueStepIndex":0,"truePropertyIndex":0,"affectsLevel":false}],"exlusiveWithNodes":[3359939809,2947148901],"randomStartProgressionBarAtProgression":0},{"nodeIndex":3,"nodeHash":3678843182,"row":0,"column":3,"prerequisiteNodeIndexes":[],"binaryPairNodeIndex":-1,"autoUnlocks":false,"lastStepRepeats":false,"isRandom":false,"isRandomRepurchasable":false,"steps":[{"stepIndex":0,"nodeStepHash":491986635,"nodeStepName":"\u30c0\u30e1\u30fc\u30b8\u5f37\u5316","nodeStepDescription":"\u3053\u306e\u6b66\u5668\u306e\u653b\u6483\u529b\u3092\u4e0a\u6607\u3055\u305b\u3066\u4e0e\u3048\u308b\u30c0\u30e1\u30fc\u30b8\u3092\u5897\u52a0\u3055\u305b\u308b\u3002","interactionDescription":"\u30a2\u30c3\u30d7\u30b0\u30ec\u30fc\u30c9","icon":"\/common\/destiny_content\/icons\/2c564a7f220855661066d6a308940940.png","damageType":0,"activationRequirement":{"gridLevel":4,"materialRequirementHashes":[3105527295,3105527294,3105527293,3105527292]},"canActivateNextStep":false,"nextStepIndex":-1,"isNextStepRandom":false,"perkHashes":[],"startProgressionBarAtProgress":7500,"statHashes":[],"affectsQuality":true,"trueStepIndex":0,"truePropertyIndex":0,"affectsLevel":false}],"exlusiveWithNodes":[],"randomStartProgressionBarAtProgression":0},{"nodeIndex":4,"nodeHash":4076480290,"row":0,"column":5,"prerequisiteNodeIndexes":[],"binaryPairNodeIndex":-1,"autoUnlocks":false,"lastStepRepeats":false,"isRandom":true,"randomActivationRequirement":{"gridLevel":0},"isRandomRepurchasable":false,"steps":[{"stepIndex":0,"nodeStepHash":3953138191,"nodeStepName":"\u30af\u30e9\u30a6\u30f3\u30fb\u30ab\u30fc\u30c8\u30ea\u30c3\u30b8","nodeStepDescription":"\u30ea\u30ed\u30fc\u30c9\u3059\u308b\u3068\u3001\u4e00\u5b9a\u306e\u78ba\u7387\u3067\u901a\u5e38\u3088\u308a\u5927\u304d\u306a\u30de\u30ac\u30b8\u30f3\u3092\u7372\u5f97\u3067\u304d\u308b\u3002","interactionDescription":"\u30a2\u30c3\u30d7\u30b0\u30ec\u30fc\u30c9","icon":"\/common\/destiny_content\/icons\/1029fc6f5ba1086258c42e1e31577be9.png","damageType":0,"activationRequirement":{"gridLevel":6,"materialRequirementHashes":[391095254]},"canActivateNextStep":false,"nextStepIndex":-1,"isNextStepRandom":true,"perkHashes":[3052118152],"startProgressionBarAtProgress":52500,"statHashes":[],"affectsQuality":false,"stepGroups":{"weaponPerformance":512,"impactEffects":0,"guardianAttributes":0,"lightAbilities":0,"damageTypes":0},"trueStepIndex":0,"truePropertyIndex":0,"affectsLevel":false},{"stepIndex":1,"nodeStepHash":4019183967,"nodeStepName":"\u30b0\u30ec\u30cd\u30fc\u30c0\u30fc","nodeStepDescription":"\u6575\u3092\u5012\u3059\u3068\u3001\u30b0\u30ec\u30cd\u30fc\u30c9\u306e\u30af\u30fc\u30eb\u30c0\u30a6\u30f3\u6642\u9593\u304c\u77ed\u7e2e\u3055\u308c\u308b\u3002","interactionDescription":"\u30a2\u30c3\u30d7\u30b0\u30ec\u30fc\u30c9","icon":"\/common\/destiny_content\/icons\/ea01cd5a7c3962ad1798ec56bb6f25dc.png","damageType":0,"activationRequirement":{"gridLevel":6,"materialRequirementHashes":[391095254]},"canActivateNextStep":false,"nextStepIndex":-1,"isNextStepRandom":true,"perkHashes":[3283108368],"startProgressionBarAtProgress":52500,"statHashes":[],"affectsQuality":false,"stepGroups":{"weaponPerformance":0,"impactEffects":0,"guardianAttributes":0,"lightAbilities":1,"damageTypes":0},"trueStepIndex":0,"truePropertyIndex":0,"affectsLevel":false},{"stepIndex":2,"nodeStepHash":1474605717,"nodeStepName":"\u5438\u5f15","nodeStepDescription":"\u3053\u306e\u6b66\u5668\u306e\u843d\u3061\u3066\u3044\u308b\u5f3e\u4e38\u306e\u56de\u53ce\u7bc4\u56f2\u304c\u5e83\u304f\u306a\u308b\u3002","interactionDescription":"\u30a2\u30c3\u30d7\u30b0\u30ec\u30fc\u30c9","icon":"\/common\/destiny_content\/icons\/412dc6211f5349af8dff0c6318c52871.png","damageType":0,"activationRequirement":{"gridLevel":6,"materialRequirementHashes":[391095254]},"canActivateNextStep":false,"nextStepIndex":-1,"isNextStepRandom":true,"perkHashes":[1989386514],"startProgressionBarAtProgress":52500,"statHashes":[],"affectsQuality":false,"stepGroups":{"weaponPerformance":512,"impactEffects":0,"guardianAttributes":0,"lightAbilities":0,"damageTypes":0},"trueStepIndex":0,"truePropertyIndex":0,"affectsLevel":false},{"stepIndex":3,"nodeStepHash":2419743018,"nodeStepName":"\u30b9\u30d4\u30fc\u30c9\u30d7\u30ec\u30a4","nodeStepDescription":"\u3053\u306e\u6b66\u5668\u306e\u9283\u5009\u304c\u7a7a\u306b\u306a\u3063\u305f\u6642\u306e\u30ea\u30ed\u30fc\u30c9\u901f\u5ea6\u304c\u4e0a\u304c\u308b\u3002","interactionDescription":"\u30a2\u30c3\u30d7\u30b0\u30ec\u30fc\u30c9","icon":"\/common\/destiny_content\/icons\/65a3714fdd2cb2506df6bd6d04f3ca41.png","damageType":0,"activationRequirement":{"gridLevel":6,"materialRequirementHashes":[391095254]},"canActivateNextStep":false,"nextStepIndex":-1,"isNextStepRandom":true,"perkHashes":[192233393],"startProgressionBarAtProgress":52500,"statHashes":[],"affectsQuality":false,"stepGroups":{"weaponPerformance":128,"impactEffects":0,"guardianAttributes":0,"lightAbilities":0,"damageTypes":0},"trueStepIndex":0,"truePropertyIndex":0,"affectsLevel":false},{"stepIndex":4,"nodeStepHash":3321026111,"nodeStepName":"\u7b2c\u4e09\u306e\u76ee","nodeStepDescription":"\u3053\u306e\u7167\u6e96\u5668\u3067\u72d9\u3044\u3092\u5b9a\u3081\u3066\u3044\u308b\u9593\u3001\u30ec\u30fc\u30c0\u30fc\u304c\u6709\u52b9\u306b\u306a\u308b\u3002","interactionDescription":"\u30a2\u30c3\u30d7\u30b0\u30ec\u30fc\u30c9","icon":"\/common\/destiny_content\/icons\/cebc6a446ed2bbd135042afcde658050.png","damageType":0,"activationRequirement":{"gridLevel":6,"materialRequirementHashes":[391095254]},"canActivateNextStep":false,"nextStepIndex":-1,"isNextStepRandom":true,"perkHashes":[770631416],"startProgressionBarAtProgress":52500,"statHashes":[],"affectsQuality":false,"stepGroups":{"weaponPerformance":0,"impactEffects":0,"guardianAttributes":32,"lightAbilities":0,"damageTypes":0},"trueStepIndex":0,"truePropertyIndex":0,"affectsLevel":false},{"stepIndex":5,"nodeStepHash":3499432131,"nodeStepName":"\u30d5\u30fc\u30ba\u30fb\u30cd\u30af\u30b9\u30c8","nodeStepDescription":"\u30de\u30ac\u30b8\u30f3\u306e\u6700\u5f8c\u306e\u4e00\u767a\u3067\u6575\u3092\u5012\u3059\u3068\u3001\u30ea\u30ed\u30fc\u30c9\u901f\u5ea6\u304c\u4e0a\u6607\u3059\u308b\u3002","interactionDescription":"\u30a2\u30c3\u30d7\u30b0\u30ec\u30fc\u30c9","icon":"\/common\/destiny_content\/icons\/2f704829126a379841a362dd5e3ec11a.png","damageType":0,"activationRequirement":{"gridLevel":6,"materialRequirementHashes":[391095254]},"canActivateNextStep":false,"nextStepIndex":-1,"isNextStepRandom":true,"perkHashes":[3686406336],"startProgressionBarAtProgress":52500,"statHashes":[],"affectsQuality":false,"stepGroups":{"weaponPerformance":128,"impactEffects":0,"guardianAttributes":0,"lightAbilities":0,"damageTypes":0},"trueStepIndex":0,"truePropertyIndex":0,"affectsLevel":false}],"exlusiveWithNodes":[],"randomStartProgressionBarAtProgression":0},{"nodeIndex":5,"nodeHash":3452924987,"row":0,"column":2,"prerequisiteNodeIndexes":[],"binaryPairNodeIndex":-1,"autoUnlocks":false,"lastStepRepeats":false,"isRandom":true,"randomActivationRequirement":{"gridLevel":0},"isRandomRepurchasable":false,"steps":[{"stepIndex":0,"nodeStepHash":1586312458,"nodeStepName":"\u30af\u30e9\u30b9\u30bf\u30fc\u7206\u5f3e","nodeStepDescription":"\u30ed\u30b1\u30c3\u30c8\u304c\u7206\u767a\u3059\u308b\u6642\u306b\u30af\u30e9\u30b9\u30bf\u30fc\u7206\u5f3e\u304c\u751f\u6210\u3055\u308c\u308b\u3002","interactionDescription":"\u30ea\u30ed\u30fc\u30eb","icon":"\/common\/destiny_content\/icons\/9291c3a5e1f9f5f9a93ab1c60b4f292b.png","damageType":0,"activationRequirement":{"gridLevel":2,"materialRequirementHashes":[391095254]},"canActivateNextStep":false,"nextStepIndex":-1,"isNextStepRandom":true,"perkHashes":[1928591453],"startProgressionBarAtProgress":0,"statHashes":[],"affectsQuality":false,"stepGroups":{"weaponPerformance":1026,"impactEffects":8,"guardianAttributes":0,"lightAbilities":0,"damageTypes":0},"trueStepIndex":0,"truePropertyIndex":0,"affectsLevel":false},{"stepIndex":1,"nodeStepHash":889898201,"nodeStepName":"\u30b0\u30ec\u30cd\u30fc\u30c9&\u30db\u30fc\u30b9\u30b7\u30e5\u30fc\u30ba","nodeStepDescription":"\u767a\u5c04\u3057\u305f\u30ed\u30b1\u30c3\u30c8\u304c\u6a19\u7684\u3068\u306e\u8ddd\u96e2\u306b\u5fdc\u3058\u3066\u65e9\u3081\u306b\u7206\u767a\u3059\u308b\u3002","interactionDescription":"\u30a2\u30c3\u30d7\u30b0\u30ec\u30fc\u30c9","icon":"\/common\/destiny_content\/icons\/11d8f24e309d29aa4d7bc707d35d2b2b.png","damageType":0,"activationRequirement":{"gridLevel":2,"materialRequirementHashes":[391095254]},"canActivateNextStep":false,"nextStepIndex":-1,"isNextStepRandom":true,"perkHashes":[2425591494],"startProgressionBarAtProgress":0,"statHashes":[],"affectsQuality":false,"stepGroups":{"weaponPerformance":1024,"impactEffects":0,"guardianAttributes":0,"lightAbilities":0,"damageTypes":0},"trueStepIndex":0,"truePropertyIndex":0,"affectsLevel":false},{"stepIndex":2,"nodeStepHash":2828711099,"nodeStepName":"\u5c48\u5f37","nodeStepDescription":"\u3053\u306e\u6b66\u5668\u3092\u4f7f\u7528\u3059\u308b\u3068\u3001\u653b\u6483\u3092\u53d7\u3051\u3066\u308b\u9593\u3082\u72d9\u3044\u3092\u3064\u3051\u3084\u3059\u304f\u306a\u308b\u3002","interactionDescription":"\u30a2\u30c3\u30d7\u30b0\u30ec\u30fc\u30c9","icon":"\/common\/destiny_content\/icons\/56b0a618702427e1257282487b7702b7.png","damageType":0,"activationRequirement":{"gridLevel":2,"materialRequirementHashes":[391095254]},"canActivateNextStep":false,"nextStepIndex":-1,"isNextStepRandom":true,"perkHashes":[2626112550],"startProgressionBarAtProgress":0,"statHashes":[],"affectsQuality":false,"stepGroups":{"weaponPerformance":0,"impactEffects":0,"guardianAttributes":16,"lightAbilities":0,"damageTypes":0},"trueStepIndex":0,"truePropertyIndex":0,"affectsLevel":false},{"stepIndex":3,"nodeStepHash":982758423,"nodeStepName":"\u30de\u30ea\u30ac\u30f3","nodeStepDescription":"\u547d\u4e2d\u3057\u306a\u304b\u3063\u305f\u5f3e\u304c\u4e00\u5b9a\u306e\u78ba\u7387\u3067\u76f4\u63a5\u30de\u30ac\u30b8\u30f3\u306b\u623b\u308b\u3002","interactionDescription":"\u30a2\u30c3\u30d7\u30b0\u30ec\u30fc\u30c9","icon":"\/common\/destiny_content\/icons\/6c5d493501c71c960b9313ef30eccf23.png","damageType":0,"activationRequirement":{"gridLevel":2,"materialRequirementHashes":[391095254]},"canActivateNextStep":false,"nextStepIndex":-1,"isNextStepRandom":true,"perkHashes":[824061322],"startProgressionBarAtProgress":0,"statHashes":[],"affectsQuality":false,"stepGroups":{"weaponPerformance":512,"impactEffects":0,"guardianAttributes":0,"lightAbilities":0,"damageTypes":0},"trueStepIndex":0,"truePropertyIndex":0,"affectsLevel":false},{"stepIndex":4,"nodeStepHash":3110691286,"nodeStepName":"\u30b5\u30fc\u30d7\u30e9\u30b9","nodeStepDescription":"\u843d\u3061\u3066\u3044\u308b\u5f3e\u85ac\u3092\u767a\u898b\u3057\u3084\u3059\u304f\u306a\u308b\u3002","interactionDescription":"\u30a2\u30c3\u30d7\u30b0\u30ec\u30fc\u30c9","icon":"\/common\/destiny_content\/icons\/d15829c40438313bb8c3226d3763e097.png","damageType":0,"activationRequirement":{"gridLevel":2,"materialRequirementHashes":[391095254]},"canActivateNextStep":false,"nextStepIndex":-1,"isNextStepRandom":true,"perkHashes":[3317503477],"startProgressionBarAtProgress":0,"statHashes":[],"affectsQuality":false,"stepGroups":{"weaponPerformance":512,"impactEffects":0,"guardianAttributes":0,"lightAbilities":0,"damageTypes":0},"trueStepIndex":0,"truePropertyIndex":0,"affectsLevel":false},{"stepIndex":5,"nodeStepHash":4178265121,"nodeStepName":"\u30c8\u30e9\u30a4\u30dd\u30c3\u30c9","nodeStepDescription":"\u3053\u306e\u30e9\u30f3\u30c1\u30e3\u30fc\u306f3\u767a\u307e\u3067\u5f3e\u3092\u88c5\u586b\u3067\u304d\u308b\u3002","interactionDescription":"\u30a2\u30c3\u30d7\u30b0\u30ec\u30fc\u30c9","icon":"\/common\/destiny_content\/icons\/df172f27e76198675ab8d8ace1ef5b19.png","damageType":0,"activationRequirement":{"gridLevel":2,"materialRequirementHashes":[391095254]},"canActivateNextStep":false,"nextStepIndex":-1,"isNextStepRandom":true,"perkHashes":[2784842908],"startProgressionBarAtProgress":0,"statHashes":[],"affectsQuality":false,"stepGroups":{"weaponPerformance":512,"impactEffects":0,"guardianAttributes":0,"lightAbilities":0,"damageTypes":0},"trueStepIndex":0,"truePropertyIndex":0,"affectsLevel":false},{"stepIndex":6,"nodeStepHash":2976905221,"nodeStepName":"\u30c8\u30e9\u30c3\u30ad\u30f3\u30b0","nodeStepDescription":"\u30db\u30fc\u30df\u30f3\u30b0\u5f3e\u3092\u6483\u3066\u308b\u3002","interactionDescription":"\u30a2\u30c3\u30d7\u30b0\u30ec\u30fc\u30c9","icon":"\/common\/destiny_content\/icons\/7fb28865684ccbca32bb642b0c66821b.png","damageType":0,"activationRequirement":{"gridLevel":2,"materialRequirementHashes":[391095254]},"canActivateNextStep":false,"nextStepIndex":-1,"isNextStepRandom":true,"perkHashes":[2179933840],"startProgressionBarAtProgress":0,"statHashes":[],"affectsQuality":false,"stepGroups":{"weaponPerformance":1024,"impactEffects":0,"guardianAttributes":0,"lightAbilities":0,"damageTypes":0},"trueStepIndex":0,"truePropertyIndex":0,"affectsLevel":false}],"exlusiveWithNodes":[],"randomStartProgressionBarAtProgression":0},{"nodeIndex":6,"nodeHash":452419628,"row":0,"column":1,"prerequisiteNodeIndexes":[],"binaryPairNodeIndex":-1,"autoUnlocks":true,"lastStepRepeats":false,"isRandom":true,"randomActivationRequirement":{"gridLevel":0},"isRandomRepurchasable":false,"steps":[{"stepIndex":0,"nodeStepHash":2873942429,"nodeStepName":"\u30a6\u30a9\u30fc\u30d8\u30c3\u30c9\u30fb\u30d9\u30cb\u30fc\u30eb","nodeStepDescription":"\u901f\u5ea6\u3068\u7206\u767a\u7bc4\u56f2\u3092\u5f37\u5316\u3059\u308b\u3002\n\u53cd\u52d5\u304c\u5927\u304d\u304f\u306a\u308b\u3002","interactionDescription":"\u30a2\u30c3\u30d7\u30b0\u30ec\u30fc\u30c9","icon":"\/common\/destiny_content\/icons\/5f850325aadf7b61a78342fc9d30687c.png","damageType":0,"activationRequirement":{"gridLevel":0,"materialRequirementHashes":[]},"canActivateNextStep":false,"nextStepIndex":-1,"isNextStepRandom":true,"perkHashes":[2868044506],"startProgressionBarAtProgress":0,"statHashes":[2523465841,3614673599,155624089],"affectsQuality":false,"stepGroups":{"weaponPerformance":1056,"impactEffects":0,"guardianAttributes":0,"lightAbilities":0,"damageTypes":0},"trueStepIndex":0,"truePropertyIndex":0,"affectsLevel":false},{"stepIndex":1,"nodeStepHash":3133678698,"nodeStepName":"\u30b3\u30f3\u30d5\u30a1\u30a4\u30f3\u30c9\u30fb\u30ed\u30fc\u30f3\u30c1","nodeStepDescription":"\u53cd\u52d5\u3092\u5927\u5e45\u306b\u8efd\u6e1b\u3059\u308b\u3002\n\u901f\u5ea6\u304c\u5927\u5e45\u306b\u843d\u3061\u308b\u3002","interactionDescription":"\u30a2\u30c3\u30d7\u30b0\u30ec\u30fc\u30c9","icon":"\/common\/destiny_content\/icons\/5f850325aadf7b61a78342fc9d30687c.png","damageType":0,"activationRequirement":{"gridLevel":0,"materialRequirementHashes":[]},"canActivateNextStep":false,"nextStepIndex":-1,"isNextStepRandom":true,"perkHashes":[],"startProgressionBarAtProgress":0,"statHashes":[2523465841,155624089],"affectsQuality":false,"stepGroups":{"weaponPerformance":32,"impactEffects":0,"guardianAttributes":0,"lightAbilities":0,"damageTypes":0},"trueStepIndex":0,"truePropertyIndex":0,"affectsLevel":false},{"stepIndex":2,"nodeStepHash":1788601689,"nodeStepName":"\u30a2\u30b0\u30ec\u30c3\u30b7\u30d6\u30b7\u30e7\u30c3\u30c8","nodeStepDescription":"\u53cd\u52d5\u304c\u898f\u5247\u7684\u306b\u306a\u308b\u3002\n\u7206\u767a\u7bc4\u56f2\u304c\u5897\u5927\u3059\u308b\u3002\n\u901f\u5ea6\u304c\u843d\u3061\u3001\u53cd\u52d5\u304c\u5927\u304d\u304f\u306a\u308b\u3002","interactionDescription":"\u30a2\u30c3\u30d7\u30b0\u30ec\u30fc\u30c9","icon":"\/common\/destiny_content\/icons\/5f850325aadf7b61a78342fc9d30687c.png","damageType":0,"activationRequirement":{"gridLevel":0,"materialRequirementHashes":[]},"canActivateNextStep":false,"nextStepIndex":-1,"isNextStepRandom":true,"perkHashes":[3097446979],"startProgressionBarAtProgress":0,"statHashes":[2523465841,3614673599,2715839340,155624089],"affectsQuality":false,"stepGroups":{"weaponPerformance":1056,"impactEffects":0,"guardianAttributes":0,"lightAbilities":0,"damageTypes":0},"trueStepIndex":0,"truePropertyIndex":0,"affectsLevel":false}],"exlusiveWithNodes":[312682976,1503756812],"randomStartProgressionBarAtProgression":0},{"nodeIndex":7,"nodeHash":1503756812,"row":2,"column":1,"prerequisiteNodeIndexes":[],"binaryPairNodeIndex":-1,"autoUnlocks":false,"lastStepRepeats":false,"isRandom":true,"randomActivationRequirement":{"gridLevel":0},"isRandomRepurchasable":false,"steps":[{"stepIndex":0,"nodeStepHash":1269129151,"nodeStepName":"\u30ab\u30a6\u30f3\u30bf\u30fc\u30de\u30b9","nodeStepDescription":"\u53cd\u52d5\u3092\u8efd\u6e1b\u3002\n\u7206\u767a\u7bc4\u56f2\u304c\u72ed\u307e\u308b\u3002","interactionDescription":"\u30a2\u30c3\u30d7\u30b0\u30ec\u30fc\u30c9","icon":"\/common\/destiny_content\/icons\/5f850325aadf7b61a78342fc9d30687c.png","damageType":0,"activationRequirement":{"gridLevel":4,"materialRequirementHashes":[2949229212]},"canActivateNextStep":false,"nextStepIndex":-1,"isNextStepRandom":true,"perkHashes":[2272440440],"startProgressionBarAtProgress":22500,"statHashes":[3614673599,155624089],"affectsQuality":false,"stepGroups":{"weaponPerformance":1056,"impactEffects":0,"guardianAttributes":0,"lightAbilities":0,"damageTypes":0},"trueStepIndex":0,"truePropertyIndex":0,"affectsLevel":false},{"stepIndex":1,"nodeStepHash":1528865420,"nodeStepName":"\u30cf\u30fc\u30c9\u30b7\u30e7\u30c3\u30c8","nodeStepDescription":"\u901f\u5ea6\u3068\u7206\u767a\u7bc4\u56f2\u3092\u5f37\u5316\u3059\u308b\u3002\n\u53cd\u52d5\u304c\u5927\u304d\u304f\u306a\u308b\u3002","interactionDescription":"\u30a2\u30c3\u30d7\u30b0\u30ec\u30fc\u30c9","icon":"\/common\/destiny_content\/icons\/5f850325aadf7b61a78342fc9d30687c.png","damageType":0,"activationRequirement":{"gridLevel":4,"materialRequirementHashes":[2949229212]},"canActivateNextStep":false,"nextStepIndex":-1,"isNextStepRandom":true,"perkHashes":[2868044506],"startProgressionBarAtProgress":22500,"statHashes":[2523465841,3614673599,155624089],"affectsQuality":false,"stepGroups":{"weaponPerformance":1056,"impactEffects":0,"guardianAttributes":0,"lightAbilities":0,"damageTypes":0},"trueStepIndex":0,"truePropertyIndex":0,"affectsLevel":false}],"exlusiveWithNodes":[312682976,452419628],"randomStartProgressionBarAtProgression":0},{"nodeIndex":8,"nodeHash":3359939809,"row":0,"column":4,"prerequisiteNodeIndexes":[],"binaryPairNodeIndex":-1,"autoUnlocks":false,"lastStepRepeats":false,"isRandom":true,"randomActivationRequirement":{"gridLevel":0},"isRandomRepurchasable":false,"steps":[{"stepIndex":0,"nodeStepHash":2623937842,"nodeStepName":"\u30af\u30a4\u30c3\u30af\u30c9\u30ed\u30fc","nodeStepDescription":"\u6b66\u5668\u3092\u9a5a\u304f\u307b\u3069\u306e\u901f\u3055\u3067\u69cb\u3048\u3089\u308c\u308b\u3002","interactionDescription":"\u30a2\u30c3\u30d7\u30b0\u30ec\u30fc\u30c9","icon":"\/common\/destiny_content\/icons\/cd3bcdfe4fb089e6b57f56ecb8f04cf1.png","damageType":0,"activationRequirement":{"gridLevel":5,"materialRequirementHashes":[391095254]},"canActivateNextStep":false,"nextStepIndex":-1,"isNextStepRandom":true,"perkHashes":[1318606268],"startProgressionBarAtProgress":37500,"statHashes":[],"affectsQuality":false,"stepGroups":{"weaponPerformance":128,"impactEffects":0,"guardianAttributes":0,"lightAbilities":0,"damageTypes":0},"trueStepIndex":0,"truePropertyIndex":0,"affectsLevel":false},{"stepIndex":1,"nodeStepHash":2364201573,"nodeStepName":"\u30d1\u30fc\u30d5\u30a7\u30af\u30c8\u30d0\u30e9\u30f3\u30b9","nodeStepDescription":"\u6b66\u5668\u306e\u53cd\u52d5\u304c\u6975\u9650\u307e\u3067\u4f4e\u4e0b\u3059\u308b\u3002","interactionDescription":"\u30a2\u30c3\u30d7\u30b0\u30ec\u30fc\u30c9","icon":"\/common\/destiny_content\/icons\/c3e046769007f47035b3e0abb2e8f92e.png","damageType":0,"activationRequirement":{"gridLevel":5,"materialRequirementHashes":[391095254]},"canActivateNextStep":false,"nextStepIndex":-1,"isNextStepRandom":true,"perkHashes":[],"startProgressionBarAtProgress":37500,"statHashes":[155624089],"affectsQuality":false,"stepGroups":{"weaponPerformance":32,"impactEffects":0,"guardianAttributes":0,"lightAbilities":0,"damageTypes":0},"trueStepIndex":0,"truePropertyIndex":0,"affectsLevel":false},{"stepIndex":2,"nodeStepHash":2202667868,"nodeStepName":"\u30d5\u30a3\u30c3\u30c8\u30b9\u30c8\u30c3\u30af","nodeStepDescription":"\u6b66\u5668\u306e\u5b89\u5b9a\u6027\u304c\u5411\u4e0a\u3059\u308b\u3002","interactionDescription":"\u30a2\u30c3\u30d7\u30b0\u30ec\u30fc\u30c9","icon":"\/common\/destiny_content\/icons\/20b4d406eb7ae0e4746aeccfcbaef2ef.png","damageType":0,"activationRequirement":{"gridLevel":5,"materialRequirementHashes":[391095254]},"canActivateNextStep":false,"nextStepIndex":-1,"isNextStepRandom":true,"perkHashes":[],"startProgressionBarAtProgress":37500,"statHashes":[155624089],"affectsQuality":false,"stepGroups":{"weaponPerformance":32,"impactEffects":0,"guardianAttributes":0,"lightAbilities":0,"damageTypes":0},"trueStepIndex":0,"truePropertyIndex":0,"affectsLevel":false}],"exlusiveWithNodes":[3872169477,2947148901],"randomStartProgressionBarAtProgression":0},{"nodeIndex":9,"nodeHash":2947148901,"row":1,"column":4,"prerequisiteNodeIndexes":[],"binaryPairNodeIndex":-1,"autoUnlocks":false,"lastStepRepeats":false,"isRandom":true,"randomActivationRequirement":{"gridLevel":0},"isRandomRepurchasable":false,"steps":[{"stepIndex":0,"nodeStepHash":31986388,"nodeStepName":"\u30d8\u30d3\u30fc\u30da\u30a4\u30ed\u30fc\u30c9","nodeStepDescription":"\u5f3e\u306e\u7206\u767a\u7bc4\u56f2\u304c\u62e1\u5927\u3059\u308b\u3002","interactionDescription":"\u30a2\u30c3\u30d7\u30b0\u30ec\u30fc\u30c9","icon":"\/common\/destiny_content\/icons\/27ef23377893d56f4fb02f1e8756b296.png","damageType":0,"activationRequirement":{"gridLevel":6,"materialRequirementHashes":[391095254]},"canActivateNextStep":false,"nextStepIndex":-1,"isNextStepRandom":true,"perkHashes":[],"startProgressionBarAtProgress":52500,"statHashes":[3614673599],"affectsQuality":false,"stepGroups":{"weaponPerformance":1024,"impactEffects":0,"guardianAttributes":0,"lightAbilities":0,"damageTypes":0},"trueStepIndex":0,"truePropertyIndex":0,"affectsLevel":false},{"stepIndex":1,"nodeStepHash":291722657,"nodeStepName":"\u30d5\u30ec\u30a2\u30de\u30b0\u30a6\u30a7\u30eb","nodeStepDescription":"\u30ea\u30ed\u30fc\u30c9\u304c\u3055\u3089\u306b\u901f\u304f\u306a\u308b\u3002","interactionDescription":"\u30a2\u30c3\u30d7\u30b0\u30ec\u30fc\u30c9","icon":"\/common\/destiny_content\/icons\/6976dbbedd7305f8e460d8ef1f35179d.png","damageType":0,"activationRequirement":{"gridLevel":6,"materialRequirementHashes":[391095254]},"canActivateNextStep":false,"nextStepIndex":-1,"isNextStepRandom":true,"perkHashes":[],"startProgressionBarAtProgress":52500,"statHashes":[4188031367],"affectsQuality":false,"stepGroups":{"weaponPerformance":128,"impactEffects":0,"guardianAttributes":0,"lightAbilities":0,"damageTypes":0},"trueStepIndex":0,"truePropertyIndex":0,"affectsLevel":false},{"stepIndex":2,"nodeStepHash":2981876675,"nodeStepName":"\u30b7\u30f3\u30b0\u30eb\u30dd\u30a4\u30f3\u30c8\u30fb\u30b9\u30ea\u30f3\u30b0","nodeStepDescription":"\u6b66\u5668\u306e\u6301\u3061\u66ff\u3048\u304c\u901f\u304f\u306a\u308b\u3002\u72d9\u3063\u3066\u3044\u308b\u6642\u306e\u79fb\u52d5\u901f\u5ea6\u3082\u901f\u304f\u306a\u308b\u3002","interactionDescription":"\u30a2\u30c3\u30d7\u30b0\u30ec\u30fc\u30c9","icon":"\/common\/destiny_content\/icons\/e695e8e3606ccf005f25a838b654ebca.png","damageType":0,"activationRequirement":{"gridLevel":6,"materialRequirementHashes":[391095254]},"canActivateNextStep":false,"nextStepIndex":-1,"isNextStepRandom":true,"perkHashes":[1543923140],"startProgressionBarAtProgress":52500,"statHashes":[],"affectsQuality":false,"stepGroups":{"weaponPerformance":64,"impactEffects":0,"guardianAttributes":0,"lightAbilities":0,"damageTypes":0},"trueStepIndex":0,"truePropertyIndex":0,"affectsLevel":false}],"exlusiveWithNodes":[3872169477,3359939809],"randomStartProgressionBarAtProgression":0},{"nodeIndex":10,"nodeHash":486779184,"row":0,"column":7,"prerequisiteNodeIndexes":[],"binaryPairNodeIndex":-1,"autoUnlocks":false,"lastStepRepeats":false,"isRandom":false,"isRandomRepurchasable":false,"steps":[{"stepIndex":0,"nodeStepHash":1277492283,"nodeStepName":"\u30c0\u30e1\u30fc\u30b8\u5f37\u5316","nodeStepDescription":"\u3053\u306e\u6b66\u5668\u306e\u653b\u6483\u529b\u3092\u4e0a\u6607\u3055\u305b\u3066\u4e0e\u3048\u308b\u30c0\u30e1\u30fc\u30b8\u3092\u5897\u52a0\u3055\u305b\u308b\u3002","interactionDescription":"\u30a2\u30c3\u30d7\u30b0\u30ec\u30fc\u30c9","icon":"\/common\/destiny_content\/icons\/2c564a7f220855661066d6a308940940.png","damageType":0,"activationRequirement":{"gridLevel":9,"materialRequirementHashes":[3984507349,3984507348,3984507351,3984507350]},"canActivateNextStep":false,"nextStepIndex":-1,"isNextStepRandom":false,"perkHashes":[],"startProgressionBarAtProgress":97500,"statHashes":[],"affectsQuality":true,"trueStepIndex":0,"truePropertyIndex":0,"affectsLevel":false}],"exlusiveWithNodes":[],"randomStartProgressionBarAtProgression":0},{"nodeIndex":11,"nodeHash":1560693961,"row":1,"column":7,"prerequisiteNodeIndexes":[],"binaryPairNodeIndex":-1,"autoUnlocks":false,"lastStepRepeats":false,"isRandom":false,"isRandomRepurchasable":false,"steps":[{"stepIndex":0,"nodeStepHash":4227382570,"nodeStepName":"\u30c0\u30e1\u30fc\u30b8\u5f37\u5316","nodeStepDescription":"\u3053\u306e\u6b66\u5668\u306e\u653b\u6483\u529b\u3092\u4e0a\u6607\u3055\u305b\u3066\u4e0e\u3048\u308b\u30c0\u30e1\u30fc\u30b8\u3092\u5897\u52a0\u3055\u305b\u308b\u3002","interactionDescription":"\u30a2\u30c3\u30d7\u30b0\u30ec\u30fc\u30c9","icon":"\/common\/destiny_content\/icons\/2c564a7f220855661066d6a308940940.png","damageType":0,"activationRequirement":{"gridLevel":10,"materialRequirementHashes":[3984507349,3984507348,3984507351,3984507350]},"canActivateNextStep":false,"nextStepIndex":-1,"isNextStepRandom":false,"perkHashes":[],"startProgressionBarAtProgress":112500,"statHashes":[],"affectsQuality":true,"trueStepIndex":0,"truePropertyIndex":0,"affectsLevel":false}],"exlusiveWithNodes":[],"randomStartProgressionBarAtProgression":0},{"nodeIndex":12,"nodeHash":1560841054,"row":2,"column":7,"prerequisiteNodeIndexes":[],"binaryPairNodeIndex":-1,"autoUnlocks":false,"lastStepRepeats":false,"isRandom":false,"isRandomRepurchasable":false,"steps":[{"stepIndex":0,"nodeStepHash":2882305561,"nodeStepName":"\u30c0\u30e1\u30fc\u30b8\u5f37\u5316","nodeStepDescription":"\u3053\u306e\u6b66\u5668\u306e\u653b\u6483\u529b\u3092\u4e0a\u6607\u3055\u305b\u3066\u4e0e\u3048\u308b\u30c0\u30e1\u30fc\u30b8\u3092\u5897\u52a0\u3055\u305b\u308b\u3002","interactionDescription":"\u30a2\u30c3\u30d7\u30b0\u30ec\u30fc\u30c9","icon":"\/common\/destiny_content\/icons\/2c564a7f220855661066d6a308940940.png","damageType":0,"activationRequirement":{"gridLevel":11,"materialRequirementHashes":[3984507349,3984507348,3984507351,3984507350]},"canActivateNextStep":false,"nextStepIndex":-1,"isNextStepRandom":false,"perkHashes":[],"startProgressionBarAtProgress":127500,"statHashes":[],"affectsQuality":true,"trueStepIndex":0,"truePropertyIndex":0,"affectsLevel":false}],"exlusiveWithNodes":[],"randomStartProgressionBarAtProgression":0},{"nodeIndex":13,"nodeHash":99489719,"row":0,"column":6,"prerequisiteNodeIndexes":[],"binaryPairNodeIndex":-1,"autoUnlocks":false,"lastStepRepeats":false,"isRandom":false,"isRandomRepurchasable":false,"steps":[{"stepIndex":0,"nodeStepHash":491986635,"nodeStepName":"\u30c0\u30e1\u30fc\u30b8\u5f37\u5316","nodeStepDescription":"\u3053\u306e\u6b66\u5668\u306e\u653b\u6483\u529b\u3092\u4e0a\u6607\u3055\u305b\u3066\u4e0e\u3048\u308b\u30c0\u30e1\u30fc\u30b8\u3092\u5897\u52a0\u3055\u305b\u308b\u3002","interactionDescription":"\u30a2\u30c3\u30d7\u30b0\u30ec\u30fc\u30c9","icon":"\/common\/destiny_content\/icons\/2c564a7f220855661066d6a308940940.png","damageType":0,"activationRequirement":{"gridLevel":8,"materialRequirementHashes":[3984475350,3984475351,3984475348,3984475349]},"canActivateNextStep":false,"nextStepIndex":-1,"isNextStepRandom":false,"perkHashes":[],"startProgressionBarAtProgress":67500,"statHashes":[],"affectsQuality":true,"trueStepIndex":0,"truePropertyIndex":0,"affectsLevel":false}],"exlusiveWithNodes":[],"randomStartProgressionBarAtProgression":0}],"calcMaxGridLevel":0,"calcProgressToMaxLevel":0}},"statGroups":{"660767731":{"statGroupHash":660767731,"maximumValue":100,"uiPosition":0,"scaledStats":[{"statHash":4284893193,"maximumValue":100,"displayAsNumeric":false,"displayInterpolation":[{"value":0,"weight":2},{"value":100,"weight":25}]},{"statHash":3614673599,"maximumValue":100,"displayAsNumeric":false,"displayInterpolation":[{"value":0,"weight":60},{"value":100,"weight":100}]},{"statHash":2523465841,"maximumValue":100,"displayAsNumeric":false,"displayInterpolation":[{"value":0,"weight":30},{"value":100,"weight":90}]},{"statHash":155624089,"maximumValue":100,"displayAsNumeric":false,"displayInterpolation":[{"value":0,"weight":15},{"value":100,"weight":100}]},{"statHash":4188031367,"maximumValue":100,"displayAsNumeric":false,"displayInterpolation":[{"value":0,"weight":30},{"value":100,"weight":100}]},{"statHash":3871231066,"maximumValue":100,"displayAsNumeric":true,"displayInterpolation":[{"value":0,"weight":1},{"value":20,"weight":1},{"value":30,"weight":2},{"value":100,"weight":2}]}],"overrides":{}}},"progressionMappings":{},"sources":{},"progressions":{"1054627247":{"progressionHash":1054627247,"name":"weapon_superior_rocket_launcher","scope":2,"repeatLastStep":true,"icon":"\/common\/destiny_content\/icons\/50604f045806a269460f0ff6e5a5267f.png","steps":[{"progressTotal":0},{"progressTotal":7500},{"progressTotal":15000}]}},"materialRequirements":{},"factions":{},"events":{},"vendorSummaries":{},"activityBundles":{},"books":{}}}